Workbook

Sheet 说明与覆盖
A1: Reddit 动物社区 Best 帖子汇总
A2: 抓取时间（UTC）：2026-08-05T11:55:18.816Z ｜ 排序：best ｜ 来源：登录状态下的 Chrome + old.reddit.com 页面
A3: 覆盖说明：帖子清单包含 11 个社区各 300 帖，共 3,300 帖。由于 Chrome 页面抓取必须逐帖打开详情页，本文件仅进一步抓取每个社区最高票帖的可见评论（best 排序、单页最多 500 条）。图片描述以标题作为代理描述，并明确标记为非逐图视觉识别。
A5: 社区 | B5: 帖子数 | C5: 有缩略图 | D5: 帖子票数合计 | E5: 帖子页评论数合计 | F5: 评论详情覆盖帖 | G5: 已抓可见评论 | H5: 未展开占位 | I5: 覆盖帖标题
A6: r/Cats | B6: =COUNTIF(帖子!$A$2:$A$3301,A6) -> 300 | C6: 271 | D6: =SUMIF(帖子!$A$2:$A$3301,A6,帖子!$H$2:$H$3301) -> 276008 | E6: =SUMIF(帖子!$A$2:$A$3301,A6,帖子!$I$2:$I$3301) -> 10959 | F6: 1 | G6: 499 | H6: 73 | I6: Found this kitten at a gas station and trying to decide what’s best for her.
A7: r/aww | B7: =COUNTIF(帖子!$A$2:$A$3301,A7) -> 300 | C7: 299 | D7: =SUMIF(帖子!$A$2:$A$3301,A7,帖子!$H$2:$H$3301) -> 247221 | E7: =SUMIF(帖子!$A$2:$A$3301,A7,帖子!$I$2:$I$3301) -> 4246 | F7: 1 | G7: 149 | H7: 0 | I7: Wife and I adopted these little nuggets yesterday!
A8: r/OneOrangeBraincell | B8: =COUNTIF(帖子!$A$2:$A$3301,A8) -> 300 | C8: 284 | D8: =SUMIF(帖子!$A$2:$A$3301,A8,帖子!$H$2:$H$3301) -> 347737 | E8: =SUMIF(帖子!$A$2:$A$3301,A8,帖子!$I$2:$I$3301) -> 5586 | F8: 1 | G8: 346 | H8: 0 | I8: This is Cheddar. He is very polite
A9: r/AnimalsBeingDerps | B9: =COUNTIF(帖子!$A$2:$A$3301,A9) -> 300 | C9: 296 | D9: =SUMIF(帖子!$A$2:$A$3301,A9,帖子!$H$2:$H$3301) -> 1355692 | E9: =SUMIF(帖子!$A$2:$A$3301,A9,帖子!$I$2:$I$3301) -> 12434 | F9: 1 | G9: 259 | H9: 0 | I9: just couldn't resist it
A10: r/blackcats | B10: =COUNTIF(帖子!$A$2:$A$3301,A10) -> 300 | C10: 288 | D10: =SUMIF(帖子!$A$2:$A$3301,A10,帖子!$H$2:$H$3301) -> 247186 | E10: =SUMIF(帖子!$A$2:$A$3301,A10,帖子!$I$2:$I$3301) -> 5622 | F10: 1 | G10: 271 | H10: 0 | I10: Kiddo went to College.. 😭
A11: r/CatDistributionSystem | B11: =COUNTIF(帖子!$A$2:$A$3301,A11) -> 300 | C11: 293 | D11: =SUMIF(帖子!$A$2:$A$3301,A11,帖子!$H$2:$H$3301) -> 726030 | E11: =SUMIF(帖子!$A$2:$A$3301,A11,帖子!$I$2:$I$3301) -> 16006 | F11: 1 | G11: 482 | H11: 17 | I11: The stray kitten that wandered into my home 2 years ago has grown up and brought home another stray kitten.
A12: r/TuxedoCats | B12: =COUNTIF(帖子!$A$2:$A$3301,A12) -> 300 | C12: 300 | D12: =SUMIF(帖子!$A$2:$A$3301,A12,帖子!$H$2:$H$3301) -> 124890 | E12: =SUMIF(帖子!$A$2:$A$3301,A12,帖子!$I$2:$I$3301) -> 4199 | F12: 1 | G12: 102 | H12: 0 | I12: Siri checking out our new home. She's like a little person! 💕
A13: r/AnimalsBeingBros | B13: =COUNTIF(帖子!$A$2:$A$3301,A13) -> 300 | C13: 258 | D13: =SUMIF(帖子!$A$2:$A$3301,A13,帖子!$H$2:$H$3301) -> 2443236 | E13: =SUMIF(帖子!$A$2:$A$3301,A13,帖子!$I$2:$I$3301) -> 17064 | F13: 1 | G13: 439 | H13: 67 | I13: In Dagestan, a hedgehog approached a passerby so that he could remove the tape from its paw. News we lack
A14: r/Catswithjobs | B14: =COUNTIF(帖子!$A$2:$A$3301,A14) -> 300 | C14: 298 | D14: =SUMIF(帖子!$A$2:$A$3301,A14,帖子!$H$2:$H$3301) -> 335212 | E14: =SUMIF(帖子!$A$2:$A$3301,A14,帖子!$I$2:$I$3301) -> 4090 | F14: 1 | G14: 252 | H14: 0 | I14: Press photograph a dead mouse caught by Larry
A15: r/WhatsWrongWithYourDog | B15: =COUNTIF(帖子!$A$2:$A$3301,A15) -> 300 | C15: 276 | D15: =SUMIF(帖子!$A$2:$A$3301,A15,帖子!$H$2:$H$3301) -> 359189 | E15: =SUMIF(帖子!$A$2:$A$3301,A15,帖子!$I$2:$I$3301) -> 6408 | F15: 1 | G15: 476 | H15: 32 | I15: This is never going to end, is it?
A16: r/rarepuppers | B16: =COUNTIF(帖子!$A$2:$A$3301,A16) -> 300 | C16: 300 | D16: =SUMIF(帖子!$A$2:$A$3301,A16,帖子!$H$2:$H$3301) -> 223549 | E16: =SUMIF(帖子!$A$2:$A$3301,A16,帖子!$I$2:$I$3301) -> 4579 | F16: 1 | G16: 134 | H16: 0 | I16: Just a happy senior boy who’s been enjoying the same patio for 12 years. 🩶
A18: 重要：Reddit 显示的票数和评论数会变化；已删除、折叠、受限或超过页面上限的评论不一定出现在“评论”表。帖子与评论原始链接均保留，便于复核。

Sheet 帖子
A1: 社区 | B1: Best 排名 | C1: 帖子 ID | D1: 帖子标题 | E1: 帖子内容 | F1: 作者 | G1: 发布时间 UTC | H1: 帖子票数 | I1: 帖子评论数 | J1: 评论抓取状态 | K1: 图片内容描述 | L1: 图片描述来源 | M1: Flair | N1: 域名/类型 | O1: 帖子链接 | P1: 媒体链接 | Q1: 缩略图链接 | R1: NSFW | S1: 排序
A2: r/cats | B2: 1 | C2: t3_1uye0qo | D2: Letting users remove posts. | F2: Merari01 | G2: 46219.845 | H2: 52 | I2: 85 | J2: 未打开详情页；仅保留评论总数 | L2: 无可见缩略图 | M2: Discussion | N2: self.cats | O2: https://old.reddit.com/r/cats/comments/1uye0qo/letting_users_remove_posts/ | P2: /r/cats/comments/1uye0qo/letting_users_remove_posts/ | R2: FALSE | S2: best
A3: r/cats | B3: 2 | C3: t3_1vg344w | D3: My best friend 2018 vs 2026. I had just found him on my neighbor's doorstep after a heavy rain | F3: ImplementLogical4130 | G3: 46239.421 | H3: 4246 | I3: 130 | J3: 未打开详情页；仅保留评论总数 | K3: 基于帖子标题推断（非逐图视觉识别）：My best friend 2018 vs 2026. I had just found him on my neighbor's doorstep after a heavy rain | L3: 帖子标题代理描述 | M3: Cat Picture - OC | N3: old.reddit.com | O3: https://old.reddit.com/r/cats/comments/1vg344w/my_best_friend_2018_vs_2026_i_had_just_found_him/ | P3: https://www.reddit.com/gallery/1vg344w | Q3: https://preview.redd.it/jooe9wvz5jhh1.png?width=140&height=105&auto=webp&s=fe176f18782136de8fc4fbc9ed71275c3c8d2ed0 | R3: FALSE | S3: best
A4: r/cats | B4: 3 | C4: t3_1vftd0w | D4: My Boy’s Tail FELL OFF! (TW for pics: pre-op stump and a separated tail) | F4: FilmBuffBrony | G4: 46239.064 | H4: 4837 | I4: 347 | J4: 未打开详情页；仅保留评论总数 | L4: 无可见缩略图 | M4: Cat Picture - OC | N4: old.reddit.com | O4: https://old.reddit.com/r/cats/comments/1vftd0w/my_boys_tail_fell_off_tw_for_pics_preop_stump_and/ | P4: https://www.reddit.com/gallery/1vftd0w | R4: TRUE | S4: best
A5: r/cats | B5: 4 | C5: t3_1vfnmgo | D5: Bart the furious | F5: DarthiusFatticus | G5: 46238.895 | H5: 13449 | I5: 122 | J5: 未打开详情页；仅保留评论总数 | K5: 基于帖子标题推断（非逐图视觉识别）：Bart the furious | L5: 帖子标题代理描述 | M5: Video - Not OC | N5: v.redd.it | O5: https://old.reddit.com/r/cats/comments/1vfnmgo/bart_the_furious/ | P5: https://v.redd.it/4hbbghdvefhh1 | Q5: https://external-preview.redd.it/N2o3cWJrZHZlZmhoMdFy-taTIW5R5LYtdcUNsnD0vk3Elp2WrYQc2NAsRbv_.png?width=140&height=140&crop=1:1,smart&format=jpg&auto=webp&s=f3712a30292dcbe364f03bb79bb8214f86efe1ba | R5: FALSE | S5: best
A6: r/cats | B6: 5 | C6: t3_1vfpxij | D6: Can you believe that I found her in the garbage? | F6: Spare_Equipment3116 | G6: 46238.959 | H6: 6435 | I6: 113 | J6: 未打开详情页；仅保留评论总数 | K6: 基于帖子标题推断（非逐图视觉识别）：Can you believe that I found her in the garbage? | L6: 帖子标题代理描述 | M6: Cat Picture - OC | N6: old.reddit.com | O6: https://old.reddit.com/r/cats/comments/1vfpxij/can_you_believe_that_i_found_her_in_the_garbage/ | P6: https://www.reddit.com/gallery/1vfpxij | Q6: https://preview.redd.it/pnml9izhvfhh1.jpg?width=140&height=140&crop=1:1,smart&auto=webp&s=4f71eb0f288afaa3289002b1831a993105227d5a | R6: FALSE | S6: best
A7: r/cats | B7: 6 | C7: t3_1vfrwvy | D7: The heartthrob, the sensitive one, and the bad boy | F7: RememberTheMaine1996 | G7: 46239.018 | H7: 4680 | I7: 99 | J7: 未打开详情页；仅保留评论总数 | K7: 基于帖子标题推断（非逐图视觉识别）：The heartthrob, the sensitive one, and the bad boy | L7: 帖子标题代理描述 | M7: Cat Picture - OC | N7: i.redd.it | O7: https://old.reddit.com/r/cats/comments/1vfrwvy/the_heartthrob_the_sensitive_one_and_the_bad_boy/ | P7: https://i.redd.it/s8nlf02maghh1.jpeg | Q7: https://preview.redd.it/s8nlf02maghh1.jpeg?width=140&height=140&crop=1:1,smart&auto=webp&s=5a1d5a570d2ee455c7975566cc76d8da711a8cc7 | R7: FALSE | S7: best
A8: r/cats | B8: 7 | C8: t3_1vfwg0r | D8: I bought a little desk toy for myself… my cat decided it belongs to him now | F8: Ok_Site2695 | G8: 46239.164 | H8: 2179 | I8: 35 | J8: 未打开详情页；仅保留评论总数 | K8: 基于帖子标题推断（非逐图视觉识别）：I bought a little desk toy for myself… my cat decided it belongs to him now | L8: 帖子标题代理描述 | M8: Video - OC | N8: v.redd.it | O8: https://old.reddit.com/r/cats/comments/1vfwg0r/i_bought_a_little_desk_toy_for_myself_my_cat/ | P8: https://v.redd.it/7r06cncvbhhh1 | Q8: https://external-preview.redd.it/ZzczcTA5ZHZiaGhoMZzvCKGiBRvgoGZIpAcHmOaenPwf8DJTF_kapeHp2CqB.png?width=140&height=140&crop=1:1,smart&format=jpg&auto=webp&s=e8c466e7287add0df14574d412fe9852d598c96d | R8: FALSE | S8: best
A9: r/cats | B9: 8 | C9: t3_1vg06ga | D9: Decided to adopt the “feral” grandpa (20) | F9: Lost_Ad_6204 | G9: 46239.303 | H9: 1095 | I9: 38 | J9: 未打开详情页；仅保留评论总数 | K9: 基于帖子标题推断（非逐图视觉识别）：Decided to adopt the “feral” grandpa (20) | L9: 帖子标题代理描述 | M9: Adoption | N9: old.reddit.com | O9: https://old.reddit.com/r/cats/comments/1vg06ga/decided_to_adopt_the_feral_grandpa_20/ | P9: https://www.reddit.com/gallery/1vg06ga | Q9: https://preview.redd.it/g9t2fa5nbihh1.jpg?width=140&height=140&crop=1:1,smart&auto=webp&s=b5e56b99d7ae6851a68d7b11bdaff43a3a30999a | R9: FALSE | S9: best
A10: r/cats | B10: 9 | C10: t3_1vfu8k3 | D10: My cat is my entire world, and I don't know what I'd do without him😭♥️ | F10: Significant_Movie814 | G10: 46239.091 | H10: 1858 | I10: 31 | J10: 未打开详情页；仅保留评论总数 | K10: 基于帖子标题推断（非逐图视觉识别）：My cat is my entire world, and I don't know what I'd do without him😭♥️ | L10: 帖子标题代理描述 | M10: Cat Picture - OC | N10: old.reddit.com | O10: https://old.reddit.com/r/cats/comments/1vfu8k3/my_cat_is_my_entire_world_and_i_dont_know_what_id/ | P10: https://www.reddit.com/gallery/1vfu8k3 | Q10: https://preview.redd.it/bb1wd68ftghh1.jpg?width=140&height=140&crop=1:1,smart&auto=webp&s=85f63145f01afff7e60e619cc07a4e7af067fbb5 | R10: FALSE | S10: best
A11: r/cats | B11: 10 | C11: t3_1vfwy88 | D11: He dragged his nuts across my cheese. | F11: lemongelee | G11: 46239.182 | H11: 1201 | I11: 124 | J11: 未打开详情页；仅保留评论总数 | K11: 基于帖子标题推断（非逐图视觉识别）：He dragged his nuts across my cheese. | L11: 帖子标题代理描述 | M11: Humor | N11: i.redd.it | O11: https://old.reddit.com/r/cats/comments/1vfwy88/he_dragged_his_nuts_across_my_cheese/ | P11: https://i.redd.it/kdrfq2yjghhh1.jpeg | Q11: https://preview.redd.it/kdrfq2yjghhh1.jpeg?width=140&height=105&auto=webp&s=adb02237e869fd698b0c0014ff61b04eba35df90 | R11: FALSE | S11: best
A12: r/cats | B12: 11 | C12: t3_1vfyge8 | D12: Cute face, smooth brain | F12: Opening_Bit_8386 | G12: 46239.237 | H12: 888 | I12: 10 | J12: 未打开详情页；仅保留评论总数 | K12: 基于帖子标题推断（非逐图视觉识别）：Cute face, smooth brain | L12: 帖子标题代理描述 | M12: Humor | N12: i.redd.it | O12: https://old.reddit.com/r/cats/comments/1vfyge8/cute_face_smooth_brain/ | P12: https://i.redd.it/h8hj33ndphhh1.png | Q12: https://preview.redd.it/h8hj33ndphhh1.png?width=140&height=140&crop=1:1,smart&auto=webp&s=00355849b6b4dbd5cd7ccdd4d91c4cb3ac88a231 | R12: FALSE | S12: best
A13: r/cats | B13: 12 | C13: t3_1vfih5j | D13: Why does she loaf like this | F13: Realistic-Wheel-7803 | G13: 46238.764 | H13: 8045 | I13: 178 | J13: 未打开详情页；仅保留评论总数 | K13: 基于帖子标题推断（非逐图视觉识别）：Why does she loaf like this | L13: 帖子标题代理描述 | M13: Cat Picture - OC | N13: old.reddit.com | O13: https://old.reddit.com/r/cats/comments/1vfih5j/why_does_she_loaf_like_this/ | P13: https://www.reddit.com/gallery/1vfih5j | Q13: https://preview.redd.it/spz38l4rgehh1.jpg?width=140&height=140&crop=1:1,smart&auto=webp&s=c8dd9e73f0e99778be11972fa00c2bc68e82e643 | R13: FALSE | S13: best
A14: r/cats | B14: 13 | C14: t3_1vfstu4 | D14: After being sick for the past few months, Sundae just had the best 12th birthday | F14: No-Yogurtcloset-1900 | G14: 46239.047 | H14: 1476 | I14: 67 | J14: 未打开详情页；仅保留评论总数 | K14: 基于帖子标题推断（非逐图视觉识别）：After being sick for the past few months, Sundae just had the best 12th birthday | L14: 帖子标题代理描述 | M14: Cat Picture - OC | N14: old.reddit.com | O14: https://old.reddit.com/r/cats/comments/1vfstu4/after_being_sick_for_the_past_few_months_sundae/ | P14: https://www.reddit.com/gallery/1vfstu4 | Q14: https://preview.redd.it/27hdl4iyhghh1.jpg?width=140&height=140&crop=1:1,smart&auto=webp&s=c3b958de6629636d58e1ada2d59b2660e5c0fd0c | R14: FALSE | S14: best
A15: r/cats | B15: 14 | C15: t3_1vfl8kn | D15: When this cat got lost and spotted his human.. | F15: _Eclipse_e | G15: 46238.833 | H15: 3708 | I15: 25 | J15: 未打开详情页；仅保留评论总数 | K15: 基于帖子标题推断（非逐图视觉识别）：When this cat got lost and spotted his human.. | L15: 帖子标题代理描述 | M15: Humor | N15: v.redd.it | O15: https://old.reddit.com/r/cats/comments/1vfl8kn/when_this_cat_got_lost_and_spotted_his_human/ | P15: https://v.redd.it/jb1t9va2zehh1 | Q15: https://external-preview.redd.it/b21yZXlxdzF6ZWhoMd6Pa4eYzmT0UtpQuFAPxs9H1GIkQkyWxpf3xM_UuAoH.png?width=140&height=140&crop=1:1,smart&format=jpg&auto=webp&s=318f9030a0d31a488bbc2b9c154fe80cb1aaace1 | R15: FALSE | S15: best
A16: r/cats | B16: 15 | C16: t3_1vg3xo9 | D16: Do your cats like sitting in boxes? | F16: Beluga_100052 | G16: 46239.451 | H16: 227 | I16: 14 | J16: 未打开详情页；仅保留评论总数 | K16: 基于帖子标题推断（非逐图视觉识别）：Do your cats like sitting in boxes? | L16: 帖子标题代理描述 | M16: Humor | N16: i.redd.it | O16: https://old.reddit.com/r/cats/comments/1vg3xo9/do_your_cats_like_sitting_in_boxes/ | P16: https://i.redd.it/sl67bj8vdjhh1.jpeg | Q16: https://preview.redd.it/sl67bj8vdjhh1.jpeg?width=140&height=140&crop=1:1,smart&auto=webp&s=5641bcb5e4967697f4e2f08c6096984c3673128d | R16: FALSE | S16: best
... A22: r/cats | B22: 21 | C22: t3_1vg1med | D22: Cat became allergic to gabapentin (she’s ok!!!) | F22: specialinterestoftw | G22: 46239.362 | H22: 138 | I22: 6 | J22: 未打开详情页；仅保留评论总数 | K22: 基于帖子标题推断（非逐图视觉识别）：Cat became allergic to gabapentin (she’s ok!!!) | L22: 帖子标题代理描述 | M22: Humor | N22: old.reddit.com | O22: https://old.reddit.com/r/cats/comments/1vg1med/cat_became_allergic_to_gabapentin_shes_ok/ | P22: https://www.reddit.com/gallery/1vg1med | Q22: https://preview.redd.it/a02eg2rtqihh1.jpg?width=140&height=105&auto=webp&s=8ec93ed60f354f111e4b69102065b3255aea5089 | R22: FALSE | S22: best
A23: r/cats | B23: 22 | C23: t3_1vf38ox | D23: Found this kitten at a gas station and trying to decide what’s best for her. | E23: Went to pump gas after clocking off work three days ago and heard a bunch of meows coming from a bush. After walking towards it, a few kitties jumped out and booked it to another bush. This one got left behind and continued to meow like crazy after I picked her up. Took her home and was contemplating on taking her to the local shelter or keeping her. However, I’m still on the fence about it because I’m not really home much and she would probably get lonely if I keep her home alone. Before making any decision though, I at least wanted to give her a name for the time being and was thinking maybe Kate or Negra. Idk im bad with names but suggestions are welcomed and any other advice. TIA | F23: Saudade_Daddy | G23: 46238.306 | H23: 39001 | I23: 1901 | J23: 已抓取该社区最高票帖的可见评论（best，最多500） | K23: 基于帖子标题推断（非逐图视觉识别）：Found this kitten at a gas station and trying to decide what’s best for her. | L23: 帖子标题代理描述 | M23: Advice | N23: i.redd.it | O23: https://old.reddit.com/r/cats/comments/1vf38ox/found_this_kitten_at_a_gas_station_and_trying_to/ | P23: https://i.redd.it/isofcixf7bhh1.jpeg | Q23: https://preview.redd.it/isofcixf7bhh1.jpeg?width=140&height=140&crop=1:1,smart&auto=webp&s=810357016d52dbe20c6eb888500df108854580ed | R23: FALSE | S23: best
A24: r/cats | B24: 23 | C24: t3_1vfzj0s | D24: Bro hears into the future | F24: PixelRealm | G24: 46239.278 | H24: 148 | I24: 13 | J24: 未打开详情页；仅保留评论总数 | K24: 基于帖子标题推断（非逐图视觉识别）：Bro hears into the future | L24: 帖子标题代理描述 | M24: Cat Picture - OC | N24: old.reddit.com | O24: https://old.reddit.com/r/cats/comments/1vfzj0s/bro_hears_into_the_future/ | P24: https://www.reddit.com/gallery/1vfzj0s | Q24: https://preview.redd.it/e67u4x195ihh1.jpg?width=140&height=140&crop=1:1,smart&auto=webp&s=10435e4a8b0decda71d254a0ff530502479ba195 | R24: FALSE | S24: best
A25: r/cats | B25: 24 | C25: t3_1vfk9ve | D25: In Memory of Toucan | F25: Cityfoghorn | G25: 46238.809 | H25: 1107 | I25: 29 | J25: 未打开详情页；仅保留评论总数 | K25: 基于帖子标题推断（非逐图视觉识别）：In Memory of Toucan | L25: 帖子标题代理描述 | M25: Mourning/Loss | N25: old.reddit.com | O25: https://old.reddit.com/r/cats/comments/1vfk9ve/in_memory_of_toucan/ | P25: https://www.reddit.com/gallery/1vfk9ve | Q25: https://preview.redd.it/rxbc9yzwsehh1.jpg?width=140&height=140&crop=1:1,smart&auto=webp&s=8954afe2b5717cfeed78f49c9d69496686fcde4a | R25: FALSE | S25: best
A26: r/cats | B26: 25 | C26: t3_1vfblf5 | D26: The boys like the dollbed | F26: TheCoralie | G26: 46238.594 | H26: 2888 | I26: 43 | J26: 未打开详情页；仅保留评论总数 | K26: 基于帖子标题推断（非逐图视觉识别）：The boys like the dollbed | L26: 帖子标题代理描述 | M26: Cat Picture - OC | N26: i.redd.it | O26: https://old.reddit.com/r/cats/comments/1vfblf5/the_boys_like_the_dollbed/ | P26: https://i.redd.it/cakytgom9dhh1.jpeg | Q26: https://preview.redd.it/cakytgom9dhh1.jpeg?width=140&height=140&crop=1:1,smart&auto=webp&s=a217b42705bb0702f6fae4bb2a161f26e346e488 | R26: FALSE | S26: best
A27: r/cats | B27: 26 | C27: t3_1vfv5bn | D27: Lil cat was brought to my condo. What should I do? | F27: SMOKEYx64 | G27: 46239.121 | H27: 264 | I27: 48 | J27: 未打开详情页；仅保留评论总数 | K27: 基于帖子标题推断（非逐图视觉识别）：Lil cat was brought to my condo. What should I do? | L27: 帖子标题代理描述 | M27: Advice | N27: i.redd.it | O27: https://old.reddit.com/r/cats/comments/1vfv5bn/lil_cat_was_brought_to_my_condo_what_should_i_do/ | P27: https://i.redd.it/d2jyhm0w0hhh1.jpeg | Q27: https://preview.redd.it/d2jyhm0w0hhh1.jpeg?width=140&height=134&auto=webp&s=ce430daf85baae0f2a4c1d8ccc0990b3b1fdc393 | R27: FALSE | S27: best
A28: r/cats | B28: 27 | C28: t3_1vfp1z0 | D28: Why does little baby sleep like this | F28: Fresh_Prize_2505 | G28: 46238.934 | H28: 606 | I28: 73 | J28: 未打开详情页；仅保留评论总数 | K28: 基于帖子标题推断（非逐图视觉识别）：Why does little baby sleep like this | L28: 帖子标题代理描述 | M28: Cat Picture - OC | N28: old.reddit.com | O28: https://old.reddit.com/r/cats/comments/1vfp1z0/why_does_little_baby_sleep_like_this/ | P28: https://www.reddit.com/gallery/1vfp1z0 | Q28: https://preview.redd.it/y1s8h7o0pfhh1.jpg?width=140&height=140&auto=webp&s=28bafbe6c8cf840fa28786c80c5e6783a6c53366 | R28: FALSE | S28: best
A29: r/cats | B29: 28 | C29: t3_1vfpoox | D29: Just adopted: first day with new cat | F29: Economy-Preference75 | G29: 46238.952 | H29: 541 | I29: 43 | J29: 未打开详情页；仅保留评论总数 | K29: 基于帖子标题推断（非逐图视觉识别）：Just adopted: first day with new cat | L29: 帖子标题代理描述 | M29: Adoption | N29: old.reddit.com | O29: https://old.reddit.com/r/cats/comments/1vfpoox/just_adopted_first_day_with_new_cat/ | P29: https://www.reddit.com/gallery/1vfpoox | Q29: https://preview.redd.it/p5ynkqfntfhh1.jpg?width=140&height=140&crop=1:1,smart&auto=webp&s=c3700bc87e3bd2dcb71512ec137ef0e88800f379 | R29: FALSE | S29: best
A30: r/cats | B30: 29 | C30: t3_1vfb880 | D30: 1 eye, 1 brain cell - meet Hange! | F30: Raquilarrr | G30: 46238.585 | H30: 2685 | I30: 50 | J30: 未打开详情页；仅保留评论总数 | K30: 基于帖子标题推断（非逐图视觉识别）：1 eye, 1 brain cell - meet Hange! | L30: 帖子标题代理描述 | M30: Cat Picture - OC | N30: old.reddit.com | O30: https://old.reddit.com/r/cats/comments/1vfb880/1_eye_1_brain_cell_meet_hange/ | P30: https://www.reddit.com/gallery/1vfb880 | Q30: https://preview.redd.it/wvu10ah57dhh1.jpg?width=140&height=140&crop=1:1,smart&auto=webp&s=6596d99a1cf48f3291049c13d717c2c055eab661 | R30: FALSE | S30: best
A31: r/cats | B31: 30 | C31: t3_1vflngu | D31: Had to say goodbye to the sweetest, snuggly boy in the whole world today. His name was Tofu | F31: KDarkOne99 | G31: 46238.843 | H31: 830 | I31: 25 | J31: 未打开详情页；仅保留评论总数 | K31: 基于帖子标题推断（非逐图视觉识别）：Had to say goodbye to the sweetest, snuggly boy in the whole world today. His name was Tofu | L31: 帖子标题代理描述 | M31: Mourning/Loss | N31: i.redd.it | O31: https://old.reddit.com/r/cats/comments/1vflngu/had_to_say_goodbye_to_the_sweetest_snuggly_boy_in/ | P31: https://i.redd.it/mwl91oqp1fhh1.jpeg | Q31: https://preview.redd.it/mwl91oqp1fhh1.jpeg?width=140&height=140&crop=1:1,smart&auto=webp&s=a248c381e0ce32a9673ead346ae91af6cac6c5c2 | R31: FALSE | S31: best
A32: r/cats | B32: 31 | C32: t3_1vg08kv | D32: I am at my wits end. What more can i even do | F32: Hannie0109 | G32: 46239.305 | H32: 104 | I32: 23 | J32: 未打开详情页；仅保留评论总数 | K32: 基于帖子标题推断（非逐图视觉识别）：I am at my wits end. What more can i even do | L32: 帖子标题代理描述 | M32: Medical Questions | N32: i.redd.it | O32: https://old.reddit.com/r/cats/comments/1vg08kv/i_am_at_my_wits_end_what_more_can_i_even_do/ | P32: https://i.redd.it/t67vcvi9cihh1.jpeg | Q32: https://preview.redd.it/t67vcvi9cihh1.jpeg?width=140&height=140&crop=1:1,smart&auto=webp&s=2ca5c1ca020aca8ba601d6ffe4309737f77115f4 | R32: FALSE | S32: best
A33: r/cats | B33: 32 | C33: t3_1vg36u5 | D33: It so hot, that my cat melted lol 😅 | F33: Boring_Apricot454 | G33: 46239.424 | H33: 63 | I33: 7 | J33: 未打开详情页；仅保留评论总数 | K33: 基于帖子标题推断（非逐图视觉识别）：It so hot, that my cat melted lol 😅 | L33: 帖子标题代理描述 | M33: Cat Picture - OC | N33: i.redd.it | O33: https://old.reddit.com/r/cats/comments/1vg36u5/it_so_hot_that_my_cat_melted_lol/ | P33: https://i.redd.it/1763vz6u6jhh1.jpeg | Q33: https://preview.redd.it/1763vz6u6jhh1.jpeg?width=140&height=140&crop=1:1,smart&auto=webp&s=e88f42e3bdff4725f5217f060ca7b6c66717d7ff | R33: FALSE | S33: best
A34: r/cats | B34: 33 | C34: t3_1vg20ud | D34: My lovely little chonky boy Hector is quite unwell🥲 | F34: LittleBoyDavy | G34: 46239.378 | H34: 70 | I34: 12 | J34: 未打开详情页；仅保留评论总数 | K34: 基于帖子标题推断（非逐图视觉识别）：My lovely little chonky boy Hector is quite unwell🥲 | L34: 帖子标题代理描述 | M34: Cat Picture - OC | N34: old.reddit.com | O34: https://old.reddit.com/r/cats/comments/1vg20ud/my_lovely_little_chonky_boy_hector_is_quite_unwell/ | P34: https://www.reddit.com/gallery/1vg20ud | Q34: https://preview.redd.it/xwzw33m1vihh1.jpg?width=140&height=140&crop=1:1,smart&auto=webp&s=1eed385c8bc33d153eb6ab4fff15ec044c7249e9 | R34: FALSE | S34: best
A35: r/cats | B35: 34 | C35: t3_1vg16we | D35: My tiny girl sleeping in my arms💕 | F35: PermissionUpstairs53 | G35: 46239.344 | H35: 74 | I35: 4 | J35: 未打开详情页；仅保留评论总数 | K35: 基于帖子标题推断（非逐图视觉识别）：My tiny girl sleeping in my arms💕 | L35: 帖子标题代理描述 | M35: Cat Picture - OC | N35: old.reddit.com | O35: https://old.reddit.com/r/cats/comments/1vg16we/my_tiny_girl_sleeping_in_my_arms/ | P35: https://www.reddit.com/gallery/1vg16we | Q35: https://preview.redd.it/vdpucj78mihh1.jpg?width=140&height=140&crop=1:1,smart&auto=webp&s=7aa62a85a7cf1ebab5d528aa0e2ed2da50e78a9f | R35: FALSE | S35: best
... A67: r/cats | B67: 66 | C67: t3_1vfbl88 | D67: It's been two weeks since we adopted this rescue cat😺 | F67: nazo_potato_0709 | G67: 46238.594 | H67: 521 | I67: 15 | J67: 未打开详情页；仅保留评论总数 | K67: 基于帖子标题推断（非逐图视觉识别）：It's been two weeks since we adopted this rescue cat😺 | L67: 帖子标题代理描述 | M67: Cat Picture - OC | N67: old.reddit.com | O67: https://old.reddit.com/r/cats/comments/1vfbl88/its_been_two_weeks_since_we_adopted_this_rescue/ | P67: https://www.reddit.com/gallery/1vfbl88 | Q67: https://preview.redd.it/wlvjmt7l9dhh1.jpg?width=140&height=140&crop=1:1,smart&auto=webp&s=fff181c26c09b70c5e589f3e357eabf3300c5812 | R67: FALSE | S67: best
A68: r/cats | B68: 67 | C68: t3_1vg1f8a | D68: I feel guilty about kit-napping my cats but it’s far too late | F68: Easteuroblondie | G68: 46239.353 | H68: 18 | I68: 10 | J68: 未打开详情页；仅保留评论总数 | L68: 无可见缩略图 | M68: Mourning/Loss | N68: self.cats | O68: https://old.reddit.com/r/cats/comments/1vg1f8a/i_feel_guilty_about_kitnapping_my_cats_but_its/ | P68: /r/cats/comments/1vg1f8a/i_feel_guilty_about_kitnapping_my_cats_but_its/ | R68: FALSE | S68: best
A69: r/cats | B69: 68 | C69: t3_1vfqlr8 | D69: Advice for pet grief | F69: PinOld7538 | G69: 46238.979 | H69: 89 | I69: 18 | J69: 未打开详情页；仅保留评论总数 | K69: 基于帖子标题推断（非逐图视觉识别）：Advice for pet grief | L69: 帖子标题代理描述 | M69: Mourning/Loss | N69: i.redd.it | O69: https://old.reddit.com/r/cats/comments/1vfqlr8/advice_for_pet_grief/ | P69: https://i.redd.it/3yudd2vl0ghh1.jpeg | Q69: https://preview.redd.it/3yudd2vl0ghh1.jpeg?width=140&height=140&crop=1:1,smart&auto=webp&s=3c9bb93d667fce28bbd8d273cd28a48f7fc89d10 | R69: FALSE | S69: best
A70: r/cats | B70: 69 | C70: t3_1vg0nll | D70: my little chubby one | F70: lumaria22 | G70: 46239.322 | H70: 20 | I70: 3 | J70: 未打开详情页；仅保留评论总数 | K70: 基于帖子标题推断（非逐图视觉识别）：my little chubby one | L70: 帖子标题代理描述 | M70: Cat Picture - OC | N70: i.redd.it | O70: https://old.reddit.com/r/cats/comments/1vg0nll/my_little_chubby_one/ | P70: https://i.redd.it/b4dmhtdmgihh1.jpeg | Q70: https://preview.redd.it/b4dmhtdmgihh1.jpeg?width=140&height=140&crop=1:1,smart&auto=webp&s=94ddf875eff30c126a4d1ff063abe4f934e1e54b | R70: FALSE | S70: best
A71: r/cats | B71: 70 | C71: t3_1vf2m82 | D71: Cancer Sucks | F71: vvenze | G71: 46238.282 | H71: 1989 | I71: 53 | J71: 未打开详情页；仅保留评论总数 | K71: 基于帖子标题推断（非逐图视觉识别）：Cancer Sucks | L71: 帖子标题代理描述 | M71: Mourning/Loss | N71: old.reddit.com | O71: https://old.reddit.com/r/cats/comments/1vf2m82/cancer_sucks/ | P71: https://www.reddit.com/gallery/1vf2m82 | Q71: https://preview.redd.it/zse9vpac1bhh1.jpg?width=140&height=140&crop=1:1,smart&auto=webp&s=d0c452439f862542507f561a3fcb1a27fc9fef0b | R71: FALSE | S71: best
A72: r/cats | B72: 71 | C72: t3_1vfp7bk | D72: if left empty and unattended this box will contain a cat | F72: ArchtonRDT | G72: 46238.938 | H72: 108 | I72: 9 | J72: 未打开详情页；仅保留评论总数 | K72: 基于帖子标题推断（非逐图视觉识别）：if left empty and unattended this box will contain a cat | L72: 帖子标题代理描述 | M72: Cat Picture - OC | N72: old.reddit.com | O72: https://old.reddit.com/r/cats/comments/1vfp7bk/if_left_empty_and_unattended_this_box_will/ | P72: https://www.reddit.com/gallery/1vfp7bk | Q72: https://preview.redd.it/bc1kiaatpfhh1.jpg?width=140&height=140&crop=1:1,smart&auto=webp&s=9d98fc4ace304ee8065de03fff6f9cd91c22985f | R72: FALSE | S72: best
A73: r/cats | B73: 72 | C73: t3_1vfyewz | D73: She always wants to read | F73: East_Potato_4082 | G73: 46239.235 | H73: 28 | I73: 6 | J73: 未打开详情页；仅保留评论总数 | K73: 基于帖子标题推断（非逐图视觉识别）：She always wants to read | L73: 帖子标题代理描述 | M73: Cat Picture - OC | N73: i.redd.it | O73: https://old.reddit.com/r/cats/comments/1vfyewz/she_always_wants_to_read/ | P73: https://i.redd.it/c0hrgw4duhhh1.jpeg | Q73: https://preview.redd.it/c0hrgw4duhhh1.jpeg?width=140&height=140&crop=1:1,smart&auto=webp&s=75aac3a260ada5a28b7515c4daba5c885eea8875 | R73: FALSE | S73: best
A74: r/cats | B74: 73 | C74: t3_1vfq8wg | D74: Thought I’d show my goofy boy Scooter | F74: Comet_Cosmos15 | G74: 46238.969 | H74: 86 | I74: 11 | J74: 未打开详情页；仅保留评论总数 | K74: 基于帖子标题推断（非逐图视觉识别）：Thought I’d show my goofy boy Scooter | L74: 帖子标题代理描述 | M74: Cat Picture - Not OC | N74: old.reddit.com | O74: https://old.reddit.com/r/cats/comments/1vfq8wg/thought_id_show_my_goofy_boy_scooter/ | P74: https://www.reddit.com/gallery/1vfq8wg | Q74: https://preview.redd.it/m0hc6t3xxfhh1.jpg?width=140&height=140&crop=1:1,smart&auto=webp&s=06222090be267f3599c825259d30104c06a6cbe2 | R74: FALSE | S74: best
A75: r/cats | B75: 74 | C75: t3_1vftmak | D75: Adopted my first cat from a shelter, acclimatizing was going great but he shut down again... | F75: delirifacient | G75: 46239.072 | H75: 54 | I75: 39 | J75: 未打开详情页；仅保留评论总数 | K75: 基于帖子标题推断（非逐图视觉识别）：Adopted my first cat from a shelter, acclimatizing was going great but he shut down again... | L75: 帖子标题代理描述 | M75: Advice | N75: i.redd.it | O75: https://old.reddit.com/r/cats/comments/1vftmak/adopted_my_first_cat_from_a_shelter_acclimatizing/ | P75: https://i.redd.it/8ya0up8ioghh1.jpeg | Q75: https://preview.redd.it/8ya0up8ioghh1.jpeg?width=140&height=140&crop=1:1,smart&auto=webp&s=546f31c4831c51079854c1d873feb0fa224de2b1 | R75: FALSE | S75: best
A76: r/cats | B76: 75 | C76: t3_1vfp6r2 | D76: Hi im Meimei | F76: tinovps | G76: 46238.938 | H76: 91 | I76: 5 | J76: 未打开详情页；仅保留评论总数 | K76: 基于帖子标题推断（非逐图视觉识别）：Hi im Meimei | L76: 帖子标题代理描述 | M76: Cat Picture - OC | N76: old.reddit.com | O76: https://old.reddit.com/r/cats/comments/1vfp6r2/hi_im_meimei/ | P76: https://www.reddit.com/gallery/1vfp6r2 | Q76: https://preview.redd.it/ocm8o98zpfhh1.jpg?width=140&height=140&crop=1:1,smart&auto=webp&s=97464f13509ce4783d86cbfa2abc810e69cbbf3c | R76: FALSE | S76: best
A77: r/cats | B77: 76 | C77: t3_1vfzs0m | D77: Found another kitty while working! | F77: FoxyLady5 | G77: 46239.287 | H77: 19 | I77: 7 | J77: 未打开详情页；仅保留评论总数 | K77: 基于帖子标题推断（非逐图视觉识别）：Found another kitty while working! | L77: 帖子标题代理描述 | M77: Cat Picture - OC | N77: i.redd.it | O77: https://old.reddit.com/r/cats/comments/1vfzs0m/found_another_kitty_while_working/ | P77: https://i.redd.it/28kt4d5q7ihh1.jpeg | Q77: https://preview.redd.it/28kt4d5q7ihh1.jpeg?width=140&height=140&crop=1:1,smart&auto=webp&s=626f4eb24745ec539529959592b2a70c3f08801d | R77: FALSE | S77: best
A78: r/cats | B78: 77 | C78: t3_1vg3rjs | D78: Cinnamon sleeps with a toy banana. | F78: Huntardlulz | G78: 46239.445 | H78: 9 | I78: 5 | J78: 未打开详情页；仅保留评论总数 | K78: 基于帖子标题推断（非逐图视觉识别）：Cinnamon sleeps with a toy banana. | L78: 帖子标题代理描述 | M78: Cat Picture - OC | N78: i.redd.it | O78: https://old.reddit.com/r/cats/comments/1vg3rjs/cinnamon_sleeps_with_a_toy_banana/ | P78: https://i.redd.it/djipuh19cjhh1.jpeg | Q78: https://preview.redd.it/djipuh19cjhh1.jpeg?width=140&height=140&crop=1:1,smart&auto=webp&s=b514614ef178c449dced7ea57c57cb2d2c8fcf70 | R78: FALSE | S78: best
A79: r/cats | B79: 78 | C79: t3_1vft7nl | D79: Why does she insist on sleeping like she's deceased | F79: glittermoney4 | G79: 46239.059 | H79: 51 | I79: 9 | J79: 未打开详情页；仅保留评论总数 | K79: 基于帖子标题推断（非逐图视觉识别）：Why does she insist on sleeping like she's deceased | L79: 帖子标题代理描述 | M79: Cat Picture - OC | N79: old.reddit.com | O79: https://old.reddit.com/r/cats/comments/1vft7nl/why_does_she_insist_on_sleeping_like_shes_deceased/ | P79: https://www.reddit.com/gallery/1vft7nl | Q79: https://preview.redd.it/jvg9sy42lghh1.jpg?width=140&height=140&crop=1:1,smart&auto=webp&s=3da6f57b56f1000bc318e040ad7fae7c9eaaafe2 | R79: FALSE | S79: best
A80: r/cats | B80: 79 | C80: t3_1vg1j3o | D80: Rescued this Queen 👸 | F80: Sufficient_Apple_611 | G80: 46239.358 | H80: 12 | I80: 5 | J80: 未打开详情页；仅保留评论总数 | K80: 基于帖子标题推断（非逐图视觉识别）：Rescued this Queen 👸 | L80: 帖子标题代理描述 | M80: Adoption | N80: old.reddit.com | O80: https://old.reddit.com/r/cats/comments/1vg1j3o/rescued_this_queen/ | P80: https://www.reddit.com/gallery/1vg1j3o | Q80: https://preview.redd.it/vj5sikvtpihh1.jpg?width=140&height=140&crop=1:1,smart&auto=webp&s=786cfdfaab5f99ff94682c8f14f1b2f062939e70 | R80: FALSE | S80: best
... A102: r/cats | B102: 101 | C102: t3_1vfu2jn | D102: Max and Bean | F102: BrightAd7127 | G102: 46239.086 | H102: 32 | I102: 3 | J102: 未打开详情页；仅保留评论总数 | K102: 基于帖子标题推断（非逐图视觉识别）：Max and Bean | L102: 帖子标题代理描述 | M102: Mourning/Loss | N102: old.reddit.com | O102: https://old.reddit.com/r/cats/comments/1vfu2jn/max_and_bean/ | P102: https://www.reddit.com/gallery/1vfu2jn | Q102: https://preview.redd.it/un6nhmh3sghh1.jpg?width=140&height=140&crop=1:1,smart&auto=webp&s=76ae7564720f8c129e475330585dc3c6f22f117f | R102: FALSE | S102: best
A103: r/cats | B103: 102 | C103: t3_1vg17ds | D103: Clever girl | F103: Rami3l | G103: 46239.344 | H103: 10 | I103: 1 | J103: 未打开详情页；仅保留评论总数 | L103: 无可见缩略图 | M103: Cat Picture - OC | N103: v.redd.it | O103: https://old.reddit.com/r/cats/comments/1vg17ds/clever_girl/ | P103: https://v.redd.it/uelfv0q6gfhh1 | R103: FALSE | S103: best
A104: r/cats | B104: 103 | C104: t3_1vfu1sx | D104: Is this weird? | F104: Interesting_Topic949 | G104: 46239.086 | H104: 31 | I104: 15 | J104: 未打开详情页；仅保留评论总数 | K104: 基于帖子标题推断（非逐图视觉识别）：Is this weird? | L104: 帖子标题代理描述 | M104: Medical Questions | N104: old.reddit.com | O104: https://old.reddit.com/r/cats/comments/1vfu1sx/is_this_weird/ | P104: https://www.reddit.com/gallery/1vfu1sx | Q104: https://preview.redd.it/v06j7wgvrghh1.jpg?width=140&height=140&crop=1:1,smart&auto=webp&s=136d5238b8598e0b0fafe654adc4ef6af84b71ce | R104: FALSE | S104: best
A105: r/cats | B105: 104 | C105: t3_1vfzf7l | D105: Do cat fart? | F105: DueButterscotch2795 | G105: 46239.274 | H105: 14 | I105: 46 | J105: 未打开详情页；仅保留评论总数 | L105: 无可见缩略图 | M105: Medical Questions | N105: self.cats | O105: https://old.reddit.com/r/cats/comments/1vfzf7l/do_cat_fart/ | P105: /r/cats/comments/1vfzf7l/do_cat_fart/ | R105: FALSE | S105: best
A106: r/cats | B106: 105 | C106: t3_1vfw18m | D106: We have a habit of putting junk on our ottoman, but it doesn't stop the cats from napping in their favorite spot | F106: Draminian | G106: 46239.15 | H106: 22 | I106: 5 | J106: 未打开详情页；仅保留评论总数 | K106: 基于帖子标题推断（非逐图视觉识别）：We have a habit of putting junk on our ottoman, but it doesn't stop the cats from napping in their favorite spot | L106: 帖子标题代理描述 | M106: Cat Picture - OC | N106: i.redd.it | O106: https://old.reddit.com/r/cats/comments/1vfw18m/we_have_a_habit_of_putting_junk_on_our_ottoman/ | P106: https://i.redd.it/tud4kh0f8hhh1.jpeg | Q106: https://preview.redd.it/tud4kh0f8hhh1.jpeg?width=140&height=105&auto=webp&s=db8116a555305e9e8f7342b65f2ccb8442761abd | R106: FALSE | S106: best
A107: r/cats | B107: 106 | C107: t3_1vet14y | D107: Why do I do this to myself?! Fostering is so HARD! 😩🫶🏼🐈‍⬛🐈 | F107: Big-Cup-13 | G107: 46237.963 | H107: 4339 | I107: 112 | J107: 未打开详情页；仅保留评论总数 | K107: 基于帖子标题推断（非逐图视觉识别）：Why do I do this to myself?! Fostering is so HARD! 😩🫶🏼🐈‍⬛🐈 | L107: 帖子标题代理描述 | M107: Adoption | N107: old.reddit.com | O107: https://old.reddit.com/r/cats/comments/1vet14y/why_do_i_do_this_to_myself_fostering_is_so_hard/ | P107: https://www.reddit.com/gallery/1vet14y | Q107: https://preview.redd.it/nwbfjager8hh1.jpg?width=140&height=140&crop=1:1,smart&auto=webp&s=55946abe21d36b531f3584020da06c10076c086d | R107: FALSE | S107: best
A108: r/cats | B108: 107 | C108: t3_1vetjgw | D108: Found her in a shed and now she’s mine. | F108: Austin5281 | G108: 46237.978 | H108: 3838 | I108: 40 | J108: 未打开详情页；仅保留评论总数 | K108: 基于帖子标题推断（非逐图视觉识别）：Found her in a shed and now she’s mine. | L108: 帖子标题代理描述 | M108: Cat Picture - OC | N108: old.reddit.com | O108: https://old.reddit.com/r/cats/comments/1vetjgw/found_her_in_a_shed_and_now_shes_mine/ | P108: https://www.reddit.com/gallery/1vetjgw | Q108: https://preview.redd.it/1dd9bzscv8hh1.jpg?width=140&height=140&crop=1:1,smart&auto=webp&s=b3dc8c12a7436c2054306c1233bbaeea6bee66e8 | R108: FALSE | S108: best
A109: r/cats | B109: 108 | C109: t3_1vg3bgb | D109: Door-side cat:work is boring, play with me☺️ | F109: Independent-Cod-2120 | G109: 46239.429 | H109: 6 | I109: 3 | J109: 未打开详情页；仅保留评论总数 | K109: 基于帖子标题推断（非逐图视觉识别）：Door-side cat:work is boring, play with me☺️ | L109: 帖子标题代理描述 | M109: Cat Picture - OC | N109: i.redd.it | O109: https://old.reddit.com/r/cats/comments/1vg3bgb/doorside_catwork_is_boring_play_with_me/ | P109: https://i.redd.it/huph426yl9gh1.jpeg | Q109: https://preview.redd.it/huph426yl9gh1.jpeg?width=140&height=140&crop=1:1,smart&auto=webp&s=3629356536311dcf9552c2430dc7c7b799b8a951 | R109: FALSE | S109: best
A110: r/cats | B110: 109 | C110: t3_1vfvt0l | D110: Bitch stole my fork | F110: WonderfulCoat7797 | G110: 46239.142 | H110: 20 | I110: 10 | J110: 未打开详情页；仅保留评论总数 | K110: 基于帖子标题推断（非逐图视觉识别）：Bitch stole my fork | L110: 帖子标题代理描述 | M110: Video - OC | N110: v.redd.it | O110: https://old.reddit.com/r/cats/comments/1vfvt0l/bitch_stole_my_fork/ | P110: https://v.redd.it/7jjhw9sc6hhh1 | Q110: https://external-preview.redd.it/OHQ3YjFyYmM2aGhoMeY8HsCQu8-MajVf8Xun9EhM-SfCCU8Sq0BJtWQZimpb.png?width=140&height=140&crop=1:1,smart&format=jpg&auto=webp&s=3968147dfba53160d867174f393023c61e355452 | R110: FALSE | S110: best
A111: r/cats | B111: 110 | C111: t3_1vesdxt | D111: To my baby boy who is now at rest, for others to know how much I loved you | F111: Decent_Criminal | G111: 46237.945 | H111: 4399 | I111: 169 | J111: 未打开详情页；仅保留评论总数 | K111: 基于帖子标题推断（非逐图视觉识别）：To my baby boy who is now at rest, for others to know how much I loved you | L111: 帖子标题代理描述 | M111: Mourning/Loss | N111: old.reddit.com | O111: https://old.reddit.com/r/cats/comments/1vesdxt/to_my_baby_boy_who_is_now_at_rest_for_others_to/ | P111: https://www.reddit.com/gallery/1vesdxt | Q111: https://preview.redd.it/27s8l75qm8hh1.jpg?width=140&height=105&auto=webp&s=e7634e9f450f34a5bec2cf971665b4524c58461d | R111: FALSE | S111: best
A112: r/cats | B112: 111 | C112: t3_1vf6glz | D112: What is my cat doing | F112: YamTabasco | G112: 46238.435 | H112: 469 | I112: 107 | J112: 未打开详情页；仅保留评论总数 | K112: 基于帖子标题推断（非逐图视觉识别）：What is my cat doing | L112: 帖子标题代理描述 | M112: Video - OC | N112: v.redd.it | O112: https://old.reddit.com/r/cats/comments/1vf6glz/what_is_my_cat_doing/ | P112: https://v.redd.it/w42py69p4chh1 | Q112: https://external-preview.redd.it/Y29wbnZkMnA0Y2hoMVP8PC9-ZSyFBAMe2VgmzrnuzC_9HqQxBGhxHDpCfoyR.png?width=140&height=140&crop=1:1,smart&format=jpg&auto=webp&s=a4f53e15b3e6afd2e09762b1d0d7c2c3e548d533 | R112: FALSE | S112: best
A113: r/cats | B113: 112 | C113: t3_1vexrpx | D113: Goodbye my beautiful, derpy boy | F113: SavMac14 | G113: 46238.107 | H113: 2008 | I113: 61 | J113: 未打开详情页；仅保留评论总数 | K113: 基于帖子标题推断（非逐图视觉识别）：Goodbye my beautiful, derpy boy | L113: 帖子标题代理描述 | M113: Mourning/Loss | N113: i.redd.it | O113: https://old.reddit.com/r/cats/comments/1vexrpx/goodbye_my_beautiful_derpy_boy/ | P113: https://i.redd.it/w5q6pqpgs9hh1.jpeg | Q113: https://preview.redd.it/w5q6pqpgs9hh1.jpeg?width=140&height=140&crop=1:1,smart&auto=webp&s=68d374f3a1ce38136c308cb9a23c8417d6dbfa2a | R113: FALSE | S113: best
A114: r/cats | B114: 113 | C114: t3_1vfq953 | D114: Chuck Doesn’t Like Green Beans | F114: sparkchaser25 | G114: 46238.969 | H114: 41 | I114: 6 | J114: 未打开详情页；仅保留评论总数 | K114: 基于帖子标题推断（非逐图视觉识别）：Chuck Doesn’t Like Green Beans | L114: 帖子标题代理描述 | M114: Cat Picture - OC | N114: i.redd.it | O114: https://old.reddit.com/r/cats/comments/1vfq953/chuck_doesnt_like_green_beans/ | P114: https://i.redd.it/i31vclbzxfhh1.jpeg | Q114: https://preview.redd.it/i31vclbzxfhh1.jpeg?width=140&height=113&auto=webp&s=e4248927bf364a953300f75f65b9caa93d6456f5 | R114: FALSE | S114: best
A115: r/cats | B115: 114 | C115: t3_1vfhsiq | D115: Show me your cats with a professional blep :p | F115: -alex_is_here- | G115: 46238.748 | H115: 108 | I115: 13 | J115: 未打开详情页；仅保留评论总数 | K115: 基于帖子标题推断（非逐图视觉识别）：Show me your cats with a professional blep :p | L115: 帖子标题代理描述 | M115: Cat Picture - OC | N115: old.reddit.com | O115: https://old.reddit.com/r/cats/comments/1vfhsiq/show_me_your_cats_with_a_professional_blep_p/ | P115: https://www.reddit.com/gallery/1vfhsiq | Q115: https://preview.redd.it/wk1wzct3dehh1.jpg?width=140&height=140&crop=1:1,smart&auto=webp&s=fc4759c42890f2b9a91cd9fe09deaf41f1eef899 | R115: FALSE | S115: best
A116: r/cats | B116: 115 | C116: t3_1vfpjmx | D116: Somebody get this Beggar out of here. | F116: Kannhil | G116: 46238.948 | H116: 44 | I116: 7 | J116: 未打开详情页；仅保留评论总数 | K116: 基于帖子标题推断（非逐图视觉识别）：Somebody get this Beggar out of here. | L116: 帖子标题代理描述 | M116: Cat Picture - OC | N116: i.redd.it | O116: https://old.reddit.com/r/cats/comments/1vfpjmx/somebody_get_this_beggar_out_of_here/ | P116: https://i.redd.it/l090ppjmsfhh1.jpeg | Q116: https://preview.redd.it/l090ppjmsfhh1.jpeg?width=140&height=140&crop=1:1,smart&auto=webp&s=c4097d2be901b43f2376bea4a8ea0a6147d552a3 | R116: FALSE | S116: best
A117: r/cats | B117: 116 | C117: t3_1vf8p55 | D117: Adopted a cat, first time cat owner🐯 | F117: Impressive_Nose_3310 | G117: 46238.512 | H117: 304 | I117: 30 | J117: 未打开详情页；仅保留评论总数 | K117: 基于帖子标题推断（非逐图视觉识别）：Adopted a cat, first time cat owner🐯 | L117: 帖子标题代理描述 | M117: Adoption | N117: i.redd.it | O117: https://old.reddit.com/r/cats/comments/1vf8p55/adopted_a_cat_first_time_cat_owner/ | P117: https://i.redd.it/acbrek3kochh1.jpeg | Q117: https://preview.redd.it/acbrek3kochh1.jpeg?width=140&height=140&crop=1:1,smart&auto=webp&s=c4f26e4752647b58496af9d6675c0e985c469128 | R117: FALSE | S117: best
... A136: r/cats | B136: 135 | C136: t3_1vfrr1n | D136: Meet Michin. He showed up one day and decided he lived here. Now he's family ❤️🐈 | F136: Bambibloomboudoir | G136: 46239.013 | H136: 26 | I136: 1 | J136: 未打开详情页；仅保留评论总数 | K136: 基于帖子标题推断（非逐图视觉识别）：Meet Michin. He showed up one day and decided he lived here. Now he's family ❤️🐈 | L136: 帖子标题代理描述 | M136: Cat Picture - OC | N136: i.redd.it | O136: https://old.reddit.com/r/cats/comments/1vfrr1n/meet_michin_he_showed_up_one_day_and_decided_he/ | P136: https://i.redd.it/ud71irva9ghh1.jpeg | Q136: https://preview.redd.it/ud71irva9ghh1.jpeg?width=140&height=140&crop=1:1,smart&auto=webp&s=10effa30af2a5a46ef93735bc683d785fbb79d70 | R136: FALSE | S136: best
A137: r/cats | B137: 136 | C137: t3_1vfv6pb | D137: Too cute not to share | F137: Evening_Protection33 | G137: 46239.122 | H137: 16 | I137: 0 | J137: 未打开详情页；仅保留评论总数 | L137: 无可见缩略图 | M137: Video - OC | N137: v.redd.it | O137: https://old.reddit.com/r/cats/comments/1vfv6pb/too_cute_not_to_share/ | P137: https://v.redd.it/d06m2hen6hgh1 | R137: FALSE | S137: best
A138: r/cats | B138: 137 | C138: t3_1vfd83o | D138: Earning a stray cat's trust is the best feeling. First head rub today😊 | F138: Repulsive-Cry2968 | G138: 46238.635 | H138: 136 | I138: 16 | J138: 未打开详情页；仅保留评论总数 | K138: 基于帖子标题推断（非逐图视觉识别）：Earning a stray cat's trust is the best feeling. First head rub today😊 | L138: 帖子标题代理描述 | M138: Cat Picture - OC | N138: v.redd.it | O138: https://old.reddit.com/r/cats/comments/1vfd83o/earning_a_stray_cats_trust_is_the_best_feeling/ | P138: https://v.redd.it/h726m516kdhh1 | Q138: https://external-preview.redd.it/cmFrNjUxdDVrZGhoMdx7C50mKcdR27sdrOtRKSCet8oSP5Gp6eeJuKg5J6k1.png?width=140&height=140&crop=1:1,smart&format=jpg&auto=webp&s=30613782d1cd3ba8df957b839ca32b0d1d5ad690 | R138: FALSE | S138: best
A139: r/cats | B139: 138 | C139: t3_1vftcnl | D139: is this cat pregnant | F139: GroundbreakingJob446 | G139: 46239.064 | H139: 20 | I139: 6 | J139: 未打开详情页；仅保留评论总数 | K139: 基于帖子标题推断（非逐图视觉识别）：is this cat pregnant | L139: 帖子标题代理描述 | M139: Medical Questions | N139: i.redd.it | O139: https://old.reddit.com/r/cats/comments/1vftcnl/is_this_cat_pregnant/ | P139: https://i.redd.it/t27ezaramghh1.jpeg | Q139: https://preview.redd.it/t27ezaramghh1.jpeg?width=140&height=140&crop=1:1,smart&auto=webp&s=a176031831134d6402608deb1034f71f3ca0a62b | R139: FALSE | S139: best
A140: r/cats | B140: 139 | C140: t3_1vftbv2 | D140: chonky cat after hitting the buffet | F140: BoodagaMeowit23 | G140: 46239.063 | H140: 20 | I140: 4 | J140: 未打开详情页；仅保留评论总数 | K140: 基于帖子标题推断（非逐图视觉识别）：chonky cat after hitting the buffet | L140: 帖子标题代理描述 | M140: Video - Not OC | N140: v.redd.it | O140: https://old.reddit.com/r/cats/comments/1vftbv2/chonky_cat_after_hitting_the_buffet/ | P140: https://v.redd.it/2wb62if1mghh1 | Q140: https://external-preview.redd.it/ODF6MmJpNzFtZ2hoMekLyBGmVojpwVmrwO-x2FcLM6OlnS4aYDrZZ9hecDti.jpeg?width=140&height=140&crop=1:1,smart&format=jpg&auto=webp&s=8f99c92bbfacd92ff952adf593db3618f727fd36 | R140: FALSE | S140: best
A141: r/cats | B141: 140 | C141: t3_1vfroah | D141: Gamer cat doing gamer cat things | F141: Moose_on_the_loose69 | G141: 46239.011 | H141: 25 | I141: 2 | J141: 未打开详情页；仅保留评论总数 | K141: 基于帖子标题推断（非逐图视觉识别）：Gamer cat doing gamer cat things | L141: 帖子标题代理描述 | M141: Cat Picture - OC | N141: old.reddit.com | O141: https://old.reddit.com/r/cats/comments/1vfroah/gamer_cat_doing_gamer_cat_things/ | P141: https://www.reddit.com/gallery/1vfroah | Q141: https://preview.redd.it/mr8zilcp8ghh1.jpg?width=140&height=140&crop=1:1,smart&auto=webp&s=55c4be99d963a3797d55a29e3c5fa030216693a0 | R141: FALSE | S141: best
A142: r/cats | B142: 141 | C142: t3_1vfz9no | D142: it’s been two years since i found him. | F142: Sharp_Surprise5936 | G142: 46239.268 | H142: 7 | I142: 5 | J142: 未打开详情页；仅保留评论总数 | K142: 基于帖子标题推断（非逐图视觉识别）：it’s been two years since i found him. | L142: 帖子标题代理描述 | M142: Cat Picture - OC | N142: old.reddit.com | O142: https://old.reddit.com/r/cats/comments/1vfz9no/its_been_two_years_since_i_found_him/ | P142: https://www.reddit.com/gallery/1vfz9no | Q142: https://preview.redd.it/l7ailjhm2ihh1.jpg?width=140&height=140&crop=1:1,smart&auto=webp&s=5505b7ccf8a12c4a4af3f84b2e819b4b75fe1bb3 | R142: FALSE | S142: best
A143: r/cats | B143: 142 | C143: t3_1vg0vuh | D143: When Your Baby Takes Over Your Work Chair? Could He At Least Do the Work Too? | F143: MaoMaosHouse | G143: 46239.331 | H143: 6 | I143: 2 | J143: 未打开详情页；仅保留评论总数 | K143: 基于帖子标题推断（非逐图视觉识别）：When Your Baby Takes Over Your Work Chair? Could He At Least Do the Work Too? | L143: 帖子标题代理描述 | M143: Cat Picture - OC | N143: self.cats | O143: https://old.reddit.com/r/cats/comments/1vg0vuh/when_your_baby_takes_over_your_work_chair_could/ | P143: /r/cats/comments/1vg0vuh/when_your_baby_takes_over_your_work_chair_could/ | Q143: https://preview.redd.it/ua789tb7jihh1.jpg?width=140&height=140&crop=1:1,smart&auto=webp&s=4082e3debc69085aae62398320014f5f2c22558c | R143: FALSE | S143: best
A144: r/cats | B144: 143 | C144: t3_1vfhl71 | D144: How much do y’all think he weighs | F144: StayLiquidy | G144: 46238.743 | H144: 81 | I144: 34 | J144: 未打开详情页；仅保留评论总数 | K144: 基于帖子标题推断（非逐图视觉识别）：How much do y’all think he weighs | L144: 帖子标题代理描述 | M144: Cat Picture - OC | N144: old.reddit.com | O144: https://old.reddit.com/r/cats/comments/1vfhl71/how_much_do_yall_think_he_weighs/ | P144: https://www.reddit.com/gallery/1vfhl71 | Q144: https://preview.redd.it/fzx5huktbehh1.jpg?width=140&height=140&crop=1:1,smart&auto=webp&s=ac759b8da7b3d099a04533bcaf432a2975fa9b53 | R144: FALSE | S144: best
A145: r/cats | B145: 144 | C145: t3_1vfav2p | D145: Olive the pampered cat | F145: yusuftetsuo | G145: 46238.575 | H145: 168 | I145: 4 | J145: 未打开详情页；仅保留评论总数 | K145: 基于帖子标题推断（非逐图视觉识别）：Olive the pampered cat | L145: 帖子标题代理描述 | M145: Cat Picture - OC | N145: old.reddit.com | O145: https://old.reddit.com/r/cats/comments/1vfav2p/olive_the_pampered_cat/ | P145: https://www.reddit.com/gallery/1vfav2p | Q145: https://preview.redd.it/as6kl2vn4dhh1.jpg?width=140&height=140&crop=1:1,smart&auto=webp&s=9b0ee368bb90c7b27b06de07c7a9a37347c80813 | R145: FALSE | S145: best
A146: r/cats | B146: 145 | C146: t3_1vg4lo1 | D146: Miss Cleopatra | F146: fantomstranger69 | G146: 46239.474 | H146: 4 | I146: 0 | J146: 未打开详情页；仅保留评论总数 | K146: 基于帖子标题推断（非逐图视觉识别）：Miss Cleopatra | L146: 帖子标题代理描述 | M146: Cat Picture - OC | N146: i.redd.it | O146: https://old.reddit.com/r/cats/comments/1vg4lo1/miss_cleopatra/ | P146: https://i.redd.it/gk44s4prjjhh1.jpeg | Q146: https://preview.redd.it/gk44s4prjjhh1.jpeg?width=140&height=140&crop=1:1,smart&auto=webp&s=2c2c07312fe68f30db376e8dce7e9591e730093d | R146: FALSE | S146: best
A147: r/cats | B147: 146 | C147: t3_1vfxhq5 | D147: Lower cost dental in the NYC Area? | F147: PenVsPaper | G147: 46239.201 | H147: 10 | I147: 4 | J147: 未打开详情页；仅保留评论总数 | K147: 基于帖子标题推断（非逐图视觉识别）：Lower cost dental in the NYC Area? | L147: 帖子标题代理描述 | M147: Advice | N147: i.redd.it | O147: https://old.reddit.com/r/cats/comments/1vfxhq5/lower_cost_dental_in_the_nyc_area/ | P147: https://i.redd.it/nlkegdrllhhh1.jpeg | Q147: https://preview.redd.it/nlkegdrllhhh1.jpeg?width=140&height=140&crop=1:1,smart&auto=webp&s=d7542f086de8a56df79c3fe4f6ed31a9363a8ca0 | R147: FALSE | S147: best
A148: r/cats | B148: 147 | C148: t3_1vfr7lk | D148: What’s going on with this kitty’s belly/breathing? | F148: DifficultFly5820 | G148: 46238.998 | H148: 22 | I148: 41 | J148: 未打开详情页；仅保留评论总数 | K148: 基于帖子标题推断（非逐图视觉识别）：What’s going on with this kitty’s belly/breathing? | L148: 帖子标题代理描述 | M148: Medical Questions | N148: v.redd.it | O148: https://old.reddit.com/r/cats/comments/1vfr7lk/whats_going_on_with_this_kittys_bellybreathing/ | P148: https://v.redd.it/dq46zcs95ghh1 | Q148: https://external-preview.redd.it/enRkNHY3bDk1Z2hoMdFFgu52l6a9seT-v7p_gsdMiF4z4apjvdQW8Kso-K-W.png?width=140&height=140&crop=1:1,smart&format=jpg&auto=webp&s=aef1f12361d3e9b8fdc5bcbf672e6adfbef8a210 | R148: FALSE | S148: best
A149: r/cats | B149: 148 | C149: t3_1vfxy0b | D149: This is how i woke up this morning 😂 | F149: Lovelots0822 | G149: 46239.217 | H149: 9 | I149: 2 | J149: 未打开详情页；仅保留评论总数 | K149: 基于帖子标题推断（非逐图视觉识别）：This is how i woke up this morning 😂 | L149: 帖子标题代理描述 | M149: Cat Picture - OC | N149: i.redd.it | O149: https://old.reddit.com/r/cats/comments/1vfxy0b/this_is_how_i_woke_up_this_morning/ | P149: https://i.redd.it/qa9gz95sphhh1.jpeg | Q149: https://preview.redd.it/qa9gz95sphhh1.jpeg?width=140&height=140&crop=1:1,smart&auto=webp&s=c1aefaf9a258bb383ad95c70e4a2e8663f01422d | R149: FALSE | S149: best
... A161: r/cats | B161: 160 | C161: t3_1vfo2my | D161: Someone decided I wasn’t allowed to go to work | F161: Vexra | G161: 46238.907 | H161: 29 | I161: 1 | J161: 未打开详情页；仅保留评论总数 | K161: 基于帖子标题推断（非逐图视觉识别）：Someone decided I wasn’t allowed to go to work | L161: 帖子标题代理描述 | M161: Cat Picture - OC | N161: i.redd.it | O161: https://old.reddit.com/r/cats/comments/1vfo2my/someone_decided_i_wasnt_allowed_to_go_to_work/ | P161: https://i.redd.it/w6nhgwc2ifhh1.jpeg | Q161: https://preview.redd.it/w6nhgwc2ifhh1.jpeg?width=140&height=140&crop=1:1,smart&auto=webp&s=1f234e5acf6ea93c956b324321d81e16fc22c628 | R161: FALSE | S161: best
A162: r/cats | B162: 161 | C162: t3_1vfyzh2 | D162: A month since Samson left me (>12, probably older) | F162: DriverAdditional1437 | G162: 46239.257 | H162: 6 | I162: 0 | J162: 未打开详情页；仅保留评论总数 | L162: 无可见缩略图 | M162: Mourning/Loss | N162: reddit.com | O162: https://old.reddit.com/r/cats/comments/1vfyzh2/a_month_since_samson_left_me_12_probably_older/ | P162: https://www.reddit.com/gallery/1vegucv | R162: FALSE | S162: best
A163: r/cats | B163: 162 | C163: t3_1vfr07z | D163: Need help for quality of life for my cat. Please help. | F163: SnooKiwis4959 | G163: 46238.991 | H163: 19 | I163: 16 | J163: 未打开详情页；仅保留评论总数 | K163: 基于帖子标题推断（非逐图视觉识别）：Need help for quality of life for my cat. Please help. | L163: 帖子标题代理描述 | M163: Advice | N163: old.reddit.com | O163: https://old.reddit.com/r/cats/comments/1vfr07z/need_help_for_quality_of_life_for_my_cat_please/ | P163: https://www.reddit.com/gallery/1vfr07z | Q163: https://preview.redd.it/nvcmkycq3ghh1.jpg?width=140&height=140&crop=1:1,smart&auto=webp&s=a3d1374e29392723da77c950191196dea19fc76b | R163: FALSE | S163: best
A164: r/cats | B164: 163 | C164: t3_1vfx39a | D164: My new outdoor cat Odyssey! | F164: Big-Yogurtcloset-74 | G164: 46239.187 | H164: 8 | I164: 1 | J164: 未打开详情页；仅保留评论总数 | K164: 基于帖子标题推断（非逐图视觉识别）：My new outdoor cat Odyssey! | L164: 帖子标题代理描述 | M164: Cat Picture - OC | N164: old.reddit.com | O164: https://old.reddit.com/r/cats/comments/1vfx39a/my_new_outdoor_cat_odyssey/ | P164: https://www.reddit.com/gallery/1vfx39a | Q164: https://preview.redd.it/uwh90imvhhhh1.jpg?width=140&height=140&crop=1:1,smart&auto=webp&s=d185caf3dc664bc854b9fe96cb9c2df92742aaca | R164: FALSE | S164: best
A165: r/cats | B165: 164 | C165: t3_1vfg64i | D165: Our two family members since 2020 | F165: SilvanuZ | G165: 46238.708 | H165: 64 | I165: 3 | J165: 未打开详情页；仅保留评论总数 | K165: 基于帖子标题推断（非逐图视觉识别）：Our two family members since 2020 | L165: 帖子标题代理描述 | M165: Cat Picture - OC | N165: old.reddit.com | O165: https://old.reddit.com/r/cats/comments/1vfg64i/our_two_family_members_since_2020/ | P165: https://www.reddit.com/gallery/1vfg64i | Q165: https://preview.redd.it/m1763o152ehh1.png?width=140&height=140&crop=1:1,smart&auto=webp&s=4cc2eb84c2928fd2de5df25bd9cbd66910e6c5cc | R165: FALSE | S165: best
A166: r/cats | B166: 165 | C166: t3_1vfqeva | D166: My Turbo ❤️ | F166: Wonderful_Ad2875 | G166: 46238.974 | H166: 18 | I166: 1 | J166: 未打开详情页；仅保留评论总数 | K166: 基于帖子标题推断（非逐图视觉识别）：My Turbo ❤️ | L166: 帖子标题代理描述 | M166: Cat Picture - OC | N166: old.reddit.com | O166: https://old.reddit.com/r/cats/comments/1vfqeva/my_turbo/ | P166: https://www.reddit.com/gallery/1vfqeva | Q166: https://preview.redd.it/c20l5yc5zfhh1.jpg?width=140&height=140&crop=1:1,smart&auto=webp&s=e8c5210269e3dad5d2d7a62447be9acad0cd8358 | R166: FALSE | S166: best
A167: r/cats | B167: 166 | C167: t3_1vfwu6a | D167: Philadelphia Cream Cheese Collins says hi y’all 🐮🐾 | F167: PositiveLilCucumber | G167: 46239.177 | H167: 8 | I167: 1 | J167: 未打开详情页；仅保留评论总数 | L167: 无可见缩略图 | M167: Cat Picture - OC | N167: reddit.com | O167: https://old.reddit.com/r/cats/comments/1vfwu6a/philadelphia_cream_cheese_collins_says_hi_yall/ | P167: https://www.reddit.com/gallery/1vfodib | R167: FALSE | S167: best
A168: r/cats | B168: 167 | C168: t3_1vf74z3 | D168: What the...... | F168: Particular_Metal4484 | G168: 46238.46 | H168: 189 | I168: 12 | J168: 未打开详情页；仅保留评论总数 | K168: 基于帖子标题推断（非逐图视觉识别）：What the...... | L168: 帖子标题代理描述 | M168: Humor | N168: i.redd.it | O168: https://old.reddit.com/r/cats/comments/1vf74z3/what_the/ | P168: https://i.redd.it/mbwl95m1bchh1.jpeg | Q168: https://preview.redd.it/mbwl95m1bchh1.jpeg?width=140&height=135&auto=webp&s=a0d0c366f45177e8281ea5b486807ffd4d46105c | R168: FALSE | S168: best
A169: r/cats | B169: 168 | C169: t3_1vfaln1 | D169: Crochet strawberry hat😗 | F169: Legitimate-Waltz-867 | G169: 46238.568 | H169: 111 | I169: 9 | J169: 未打开详情页；仅保留评论总数 | K169: 基于帖子标题推断（非逐图视觉识别）：Crochet strawberry hat😗 | L169: 帖子标题代理描述 | M169: Cat Picture - OC | N169: old.reddit.com | O169: https://old.reddit.com/r/cats/comments/1vfaln1/crochet_strawberry_hat/ | P169: https://www.reddit.com/gallery/1vfaln1 | Q169: https://preview.redd.it/sjsmdu0u2dhh1.jpg?width=140&height=140&crop=1:1,smart&auto=webp&s=ea7dcadc1fb1c647f6f9e7840102d158e7775cfc | R169: FALSE | S169: best
A170: r/cats | B170: 169 | C170: t3_1vetbvp | D170: Constantly licking me! | F170: catwithmacaroni | G170: 46237.972 | H170: 1587 | I170: 38 | J170: 未打开详情页；仅保留评论总数 | K170: 基于帖子标题推断（非逐图视觉识别）：Constantly licking me! | L170: 帖子标题代理描述 | M170: Advice | N170: old.reddit.com | O170: https://old.reddit.com/r/cats/comments/1vetbvp/constantly_licking_me/ | P170: https://www.reddit.com/gallery/1vetbvp | Q170: https://preview.redd.it/ur4rvr3rt8hh1.jpg?width=140&height=105&auto=webp&s=4b758ccd8e7951e55c6710ba17aba3fc3902f428 | R170: FALSE | S170: best
A171: r/cats | B171: 170 | C171: t3_1vfuz63 | D171: Art Director Hana supervising my work | F171: Regular-Forever-3251 | G171: 46239.115 | H171: 10 | I171: 1 | J171: 未打开详情页；仅保留评论总数 | K171: 基于帖子标题推断（非逐图视觉识别）：Art Director Hana supervising my work | L171: 帖子标题代理描述 | M171: Video - OC | N171: v.redd.it | O171: https://old.reddit.com/r/cats/comments/1vfuz63/art_director_hana_supervising_my_work/ | P171: https://v.redd.it/1dzn50ldzghh1 | Q171: https://external-preview.redd.it/dWY3aHZ4aWR6Z2hoMTLooqMP9JJZ62aCVERKhvviW_eFFH6pq2OornNuTQbr.jpeg?width=140&height=78&format=jpg&auto=webp&s=96d2f7efe609ebc44736d856ccd39566624a1fff | R171: FALSE | S171: best
A172: r/cats | B172: 171 | C172: t3_1vex4k6 | D172: Cat distribution system delivered | F172: dumbfuckdipa | G172: 46238.087 | H172: 912 | I172: 23 | J172: 未打开详情页；仅保留评论总数 | K172: 基于帖子标题推断（非逐图视觉识别）：Cat distribution system delivered | L172: 帖子标题代理描述 | M172: Cat Picture - OC | N172: old.reddit.com | O172: https://old.reddit.com/r/cats/comments/1vex4k6/cat_distribution_system_delivered/ | P172: https://www.reddit.com/gallery/1vex4k6 | Q172: https://preview.redd.it/qcojxws8n9hh1.jpg?width=140&height=140&crop=1:1,smart&auto=webp&s=774e9b8e19d8ac61881d3a6372d4e292c29bac02 | R172: FALSE | S172: best
A173: r/cats | B173: 172 | C173: t3_1vflxzd | D173: This is Salad Bar (a nickname of her official name, Salazar) aka Salad but I mostly just call her Sally. She is the most beautiful and sweet kitty ever and she won’t apologize for it. | F173: xhris49 | G173: 46238.851 | H173: 30 | I173: 6 | J173: 未打开详情页；仅保留评论总数 | K173: 基于帖子标题推断（非逐图视觉识别）：This is Salad Bar (a nickname of her official name, Salazar) aka Salad but I mostly just call her Sally. She is the most beautiful and sweet kitty ever and she won’t apologize for it. | L173: 帖子标题代理描述 | M173: Cat Picture - OC | N173: i.redd.it | O173: https://old.reddit.com/r/cats/comments/1vflxzd/this_is_salad_bar_a_nickname_of_her_official_name/ | P173: https://i.redd.it/v3ovn5am3fhh1.jpeg | Q173: https://preview.redd.it/v3ovn5am3fhh1.jpeg?width=140&height=140&crop=1:1,smart&auto=webp&s=20c13524189c902295353d651af41da016604e1b | R173: FALSE | S173: best
A174: r/cats | B174: 173 | C174: t3_1vfsuev | D174: Sharp face | F174: beepboop998 | G174: 46239.047 | H174: 11 | I174: 5 | J174: 未打开详情页；仅保留评论总数 | K174: 基于帖子标题推断（非逐图视觉识别）：Sharp face | L174: 帖子标题代理描述 | M174: Cat Picture - OC | N174: old.reddit.com | O174: https://old.reddit.com/r/cats/comments/1vfsuev/sharp_face/ | P174: https://www.reddit.com/gallery/1vfsuev | Q174: https://preview.redd.it/2qea2hz3ighh1.jpg?width=140&height=140&crop=1:1,smart&auto=webp&s=d632b527377dab03fe6294eb603177817bab45bf | R174: FALSE | S174: best
A175: r/cats | B175: 174 | C175: t3_1vfvgcz | D175: My cats whiskers are so long she reminds me of the Caroline guy | F175: Effective_Sun7405 | G175: 46239.13 | H175: 8 | I175: 3 | J175: 未打开详情页；仅保留评论总数 | K175: 基于帖子标题推断（非逐图视觉识别）：My cats whiskers are so long she reminds me of the Caroline guy | L175: 帖子标题代理描述 | M175: Humor | N175: old.reddit.com | O175: https://old.reddit.com/r/cats/comments/1vfvgcz/my_cats_whiskers_are_so_long_she_reminds_me_of/ | P175: https://www.reddit.com/gallery/1vfvgcz | Q175: https://preview.redd.it/i7v0bsnc3hhh1.jpg?width=140&height=140&crop=1:1,smart&auto=webp&s=c919fc4698247feac059c3b7636d0810bd588f34 | R175: FALSE | S175: best
A176: r/cats | B176: 175 | C176: t3_1vfcz1t | D176: I don’t understand her motivation to bite me. | F176: Icy-Arachnid-78 | G176: 46238.629 | H176: 83 | I176: 30 | J176: 未打开详情页；仅保留评论总数 | K176: 基于帖子标题推断（非逐图视觉识别）：I don’t understand her motivation to bite me. | L176: 帖子标题代理描述 | M176: Advice | N176: old.reddit.com | O176: https://old.reddit.com/r/cats/comments/1vfcz1t/i_dont_understand_her_motivation_to_bite_me/ | P176: https://www.reddit.com/gallery/1vfcz1t | Q176: https://preview.redd.it/9lzm02tmidhh1.jpg?width=140&height=140&crop=1:1,smart&auto=webp&s=f52edcfa7f363a9ee430973a3e7f2762476e2971 | R176: FALSE | S176: best
A177: r/cats | B177: 176 | C177: t3_1vfy0yf | D177: My cow gets poofy tail when he's a happy boi. | F177: pop_rocksnthings | G177: 46239.22 | H177: 6 | I177: 2 | J177: 未打开详情页；仅保留评论总数 | L177: 无可见缩略图 | M177: Video - OC | N177: v.redd.it | O177: https://old.reddit.com/r/cats/comments/1vfy0yf/my_cow_gets_poofy_tail_when_hes_a_happy_boi/ | P177: https://v.redd.it/9vsawxc82hhh1 | R177: FALSE | S177: best
A178: r/cats | B178: 177 | C178: t3_1vfqnf4 | D178: Extra skin | F178: kitten12551 | G178: 46238.981 | H178: 17 | I178: 20 | J178: 未打开详情页；仅保留评论总数 | K178: 基于帖子标题推断（非逐图视觉识别）：Extra skin | L178: 帖子标题代理描述 | M178: Advice | N178: i.redd.it | O178: https://old.reddit.com/r/cats/comments/1vfqnf4/extra_skin/ | P178: https://i.redd.it/vhb9hiqy0ghh1.jpeg | Q178: https://preview.redd.it/vhb9hiqy0ghh1.jpeg?width=140&height=140&crop=1:1,smart&auto=webp&s=ef968c4cc4b7990dfbcce874c708d539050fc3c3 | R178: FALSE | S178: best
A179: r/cats | B179: 178 | C179: t3_1vfuj9g | D179: Meet oreo- my expressionful cat | F179: Next-Way7176 | G179: 46239.101 | H179: 10 | I179: 1 | J179: 未打开详情页；仅保留评论总数 | K179: 基于帖子标题推断（非逐图视觉识别）：Meet oreo- my expressionful cat | L179: 帖子标题代理描述 | M179: Cat Picture - OC | N179: old.reddit.com | O179: https://old.reddit.com/r/cats/comments/1vfuj9g/meet_oreo_my_expressionful_cat/ | P179: https://www.reddit.com/gallery/1vfuj9g | Q179: https://preview.redd.it/shw1iw2svghh1.jpg?width=140&height=140&crop=1:1,smart&auto=webp&s=2d376de0b87b64234e9ccf0ea87da84ebbd1b6cf | R179: FALSE | S179: best
A180: r/cats | B180: 179 | C180: t3_1vfr0a6 | D180: Lucas scents anything he's given | F180: Successful_Nail_8572 | G180: 46238.992 | H180: 16 | I180: 1 | J180: 未打开详情页；仅保留评论总数 | K180: 基于帖子标题推断（非逐图视觉识别）：Lucas scents anything he's given | L180: 帖子标题代理描述 | M180: Video - OC | N180: v.redd.it | O180: https://old.reddit.com/r/cats/comments/1vfr0a6/lucas_scents_anything_hes_given/ | P180: https://v.redd.it/avumki4l2ghh1 | Q180: https://external-preview.redd.it/ajA3ZGFlNWwyZ2hoMWVWKpswZcrkSe38nkDU4WLQ65VWfOwIG-0il8XKuPwZ.png?width=140&height=140&crop=1:1,smart&format=jpg&auto=webp&s=02bd37c7199211ce784a914d222c5b19be1e60bb | R180: FALSE | S180: best
A181: r/cats | B181: 180 | C181: t3_1vfabvk | D181: Tribute to my 19 year old Fur Baby, Prissilla. | F181: ApexRathalos038 | G181: 46238.56 | H181: 110 | I181: 9 | J181: 未打开详情页；仅保留评论总数 | K181: 基于帖子标题推断（非逐图视觉识别）：Tribute to my 19 year old Fur Baby, Prissilla. | L181: 帖子标题代理描述 | M181: Mourning/Loss | N181: old.reddit.com | O181: https://old.reddit.com/r/cats/comments/1vfabvk/tribute_to_my_19_year_old_fur_baby_prissilla/ | P181: https://www.reddit.com/gallery/1vfabvk | Q181: https://preview.redd.it/xug5q80v0dhh1.jpg?width=140&height=140&crop=1:1,smart&auto=webp&s=9cd122cfab9f1f0e24c5e9de2b74957021100db4 | R181: FALSE | S181: best
A182: r/cats | B182: 181 | C182: t3_1vg1pbu | D182: I adopt a Kitten but I feel horrible | F182: PolarGeners | G182: 46239.365 | H182: 3 | I182: 12 | J182: 未打开详情页；仅保留评论总数 | L182: 无可见缩略图 | M182: Adoption | N182: self.cats | O182: https://old.reddit.com/r/cats/comments/1vg1pbu/i_adopt_a_kitten_but_i_feel_horrible/ | P182: /r/cats/comments/1vg1pbu/i_adopt_a_kitten_but_i_feel_horrible/ | R182: FALSE | S182: best
A183: r/cats | B183: 182 | C183: t3_1vfwkta | D183: Would you trust him to do your taxes? | F183: Opening-Lie-498 | G183: 46239.168 | H183: 7 | I183: 2 | J183: 未打开详情页；仅保留评论总数 | K183: 基于帖子标题推断（非逐图视觉识别）：Would you trust him to do your taxes? | L183: 帖子标题代理描述 | M183: Cat Picture - OC | N183: i.redd.it | O183: https://old.reddit.com/r/cats/comments/1vfwkta/would_you_trust_him_to_do_your_taxes/ | P183: https://i.redd.it/5ahiemwychhh1.jpeg | Q183: https://preview.redd.it/5ahiemwychhh1.jpeg?width=140&height=140&crop=1:1,smart&auto=webp&s=5deca8ecc89434698d170feca9f0b4647d68dc2a | R183: FALSE | S183: best
A184: r/cats | B184: 183 | C184: t3_1vfed4i | D184: Besides you, what is your cat obsessed with or addicted to? | F184: mo_ah_knee | G184: 46238.664 | H184: 66 | I184: 87 | J184: 未打开详情页；仅保留评论总数 | K184: 基于帖子标题推断（非逐图视觉识别）：Besides you, what is your cat obsessed with or addicted to? | L184: 帖子标题代理描述 | M184: Humor | N184: i.redd.it | O184: https://old.reddit.com/r/cats/comments/1vfed4i/besides_you_what_is_your_cat_obsessed_with_or/ | P184: https://i.redd.it/il56m18mrdhh1.jpeg | Q184: https://preview.redd.it/il56m18mrdhh1.jpeg?width=140&height=140&crop=1:1,smart&auto=webp&s=71d2eb8d4fe4a87f66728a809056ecf850135613 | R184: FALSE | S184: best
A185: r/cats | B185: 184 | C185: t3_1vfmgav | D185: Is it normal that Bessie’s favorite hobby is cuddling with me? | F185: AAAAdragon | G185: 46238.864 | H185: 26 | I185: 7 | J185: 未打开详情页；仅保留评论总数 | K185: 基于帖子标题推断（非逐图视觉识别）：Is it normal that Bessie’s favorite hobby is cuddling with me? | L185: 帖子标题代理描述 | M185: Cat Picture - OC | N185: old.reddit.com | O185: https://old.reddit.com/r/cats/comments/1vfmgav/is_it_normal_that_bessies_favorite_hobby_is/ | P185: https://www.reddit.com/gallery/1vfmgav | Q185: https://preview.redd.it/olial5m17fhh1.jpg?width=140&height=105&auto=webp&s=6b8f1f8379e2bf6b6342131fc0a833f2a417aa6f | R185: FALSE | S185: best
A186: r/cats | B186: 185 | C186: t3_1vfpvuy | D186: "Screw you, kid!" Mira says to the new kitten | F186: gregn8r1 | G186: 46238.958 | H186: 18 | I186: 1 | J186: 未打开详情页；仅保留评论总数 | K186: 基于帖子标题推断（非逐图视觉识别）："Screw you, kid!" Mira says to the new kitten | L186: 帖子标题代理描述 | M186: Video - OC | N186: v.redd.it | O186: https://old.reddit.com/r/cats/comments/1vfpvuy/screw_you_kid_mira_says_to_the_new_kitten/ | P186: https://v.redd.it/eukpp925vfhh1 | Q186: https://external-preview.redd.it/bzdxd2NhMDV2ZmhoMQp-Oqfwzn5BzE9Ntm5CZF0rwFta5x6ba8IXsuWUibzo.png?width=140&height=140&crop=1:1,smart&format=jpg&auto=webp&s=3f75c51a13e9fe2a2bd982fe8c040409f7c34951 | R186: FALSE | S186: best
...

Sheet 评论
A1: 社区 | B1: 帖子 ID | C1: 帖子标题 | D1: 评论 ID | E1: 层级 | F1: 评论作者 | G1: 评论时间 UTC | H1: 评论票数 | I1: 评论内容 | J1: 评论链接 | K1: 帖子链接
A2: r/cats | B2: t3_1vf38ox | C2: Found this kitten at a gas station and trying to decide what’s best for her. | D2: t1_p1ltgvu | E2: 0 | F2: rdeluna | G2: 46238.31 | H2: 5986 | I2: Hmm not sure which fruits are best but I can tell that chair / home sure looks best for her. OP, looks like you’ve been chosen, if it’s possible, you’d both make a happy family. | J2: https://old.reddit.com/r/cats/comments/1vf38ox/found_this_kitten_at_a_gas_station_and_trying_to/p1ltgvu/ | K2: https://old.reddit.com/r/cats/comments/1vf38ox/found_this_kitten_at_a_gas_station_and_trying_to/
A3: r/cats | B3: t3_1vf38ox | C3: Found this kitten at a gas station and trying to decide what’s best for her. | D3: t1_p1ltf6e | E3: 0 | F3: Confident_Lecture498 | G3: 46238.31 | H3: 4221 | I3: Dang what a perfect photo | J3: https://old.reddit.com/r/cats/comments/1vf38ox/found_this_kitten_at_a_gas_station_and_trying_to/p1ltf6e/ | K3: https://old.reddit.com/r/cats/comments/1vf38ox/found_this_kitten_at_a_gas_station_and_trying_to/
A4: r/cats | B4: t3_1vf38ox | C4: Found this kitten at a gas station and trying to decide what’s best for her. | D4: t1_p1ltqn8 | E4: 0 | F4: Important_Wrap772 | G4: 46238.312 | H4: 3870 | I4: Get a second cat so they can keep each other company | J4: https://old.reddit.com/r/cats/comments/1vf38ox/found_this_kitten_at_a_gas_station_and_trying_to/p1ltqn8/ | K4: https://old.reddit.com/r/cats/comments/1vf38ox/found_this_kitten_at_a_gas_station_and_trying_to/
A5: r/cats | B5: t3_1vf38ox | C5: Found this kitten at a gas station and trying to decide what’s best for her. | D5: t1_p1lw2aw | E5: 0 | F5: Semjaja | G5: 46238.325 | H5: 2605 | I5: Not sure if I should keep her but in the meantime, let me name her and get her a collar You're not fooling anyone OP (well maybe yourself). I think she's staying... | J5: https://old.reddit.com/r/cats/comments/1vf38ox/found_this_kitten_at_a_gas_station_and_trying_to/p1lw2aw/ | K5: https://old.reddit.com/r/cats/comments/1vf38ox/found_this_kitten_at_a_gas_station_and_trying_to/
A6: r/cats | B6: t3_1vf38ox | C6: Found this kitten at a gas station and trying to decide what’s best for her. | D6: t1_p1m2dew | E6: 0 | F6: Calm_Possibility9024 | G6: 46238.362 | H6: 1858 | I6: I love how she's got her front paws on the table like she's a little human | J6: https://old.reddit.com/r/cats/comments/1vf38ox/found_this_kitten_at_a_gas_station_and_trying_to/p1m2dew/ | K6: https://old.reddit.com/r/cats/comments/1vf38ox/found_this_kitten_at_a_gas_station_and_trying_to/
A7: r/cats | B7: t3_1vf38ox | C7: Found this kitten at a gas station and trying to decide what’s best for her. | D7: t1_p1lu5in | E7: 0 | F7: twinno2 | G7: 46238.314 | H7: 1462 | I7: If you go back and snag another kitty, they will entertain each other if you keep two. | J7: https://old.reddit.com/r/cats/comments/1vf38ox/found_this_kitten_at_a_gas_station_and_trying_to/p1lu5in/ | K7: https://old.reddit.com/r/cats/comments/1vf38ox/found_this_kitten_at_a_gas_station_and_trying_to/
A8: r/cats | B8: t3_1vf38ox | C8: Found this kitten at a gas station and trying to decide what’s best for her. | D8: t1_p1lvva1 | E8: 0 | F8: Freyjia1 | G8: 46238.324 | H8: 812 | I8: Ive seen cats go nuts for watermelon and strawberries, dunno about the other 3 | J8: https://old.reddit.com/r/cats/comments/1vf38ox/found_this_kitten_at_a_gas_station_and_trying_to/p1lvva1/ | K8: https://old.reddit.com/r/cats/comments/1vf38ox/found_this_kitten_at_a_gas_station_and_trying_to/
A9: r/cats | B9: t3_1vf38ox | C9: Found this kitten at a gas station and trying to decide what’s best for her. | D9: t1_p1lx0to | E9: 0 | F9: BranFendigaidd | G9: 46238.331 | H9: 808 | I9: to not be alone, go back to the gas station, find the other kittens. Take them. Leave 2 for you and the rest find a home or a non-kill shelter (kittens are adopted extremely fast) | J9: https://old.reddit.com/r/cats/comments/1vf38ox/found_this_kitten_at_a_gas_station_and_trying_to/p1lx0to/ | K9: https://old.reddit.com/r/cats/comments/1vf38ox/found_this_kitten_at_a_gas_station_and_trying_to/
A10: r/cats | B10: t3_1vf38ox | C10: Found this kitten at a gas station and trying to decide what’s best for her. | D10: t1_p1nc28d | E10: 0 | F10: dc469 | G10: 46238.565 | H10: 685 | I10: I came to say exactly this. OP got her a collar. That was unnecessary money spent (unlike kibble or litter). They just need us to have someone tell them they made the right decision. 🥰 | J10: https://old.reddit.com/r/cats/comments/1vf38ox/found_this_kitten_at_a_gas_station_and_trying_to/p1nc28d/ | K10: https://old.reddit.com/r/cats/comments/1vf38ox/found_this_kitten_at_a_gas_station_and_trying_to/
A11: r/cats | B11: t3_1vf38ox | C11: Found this kitten at a gas station and trying to decide what’s best for her. | D11: t1_p1m5y02 | E11: 0 | F11: Valkyriesride1 | G11: 46238.382 | H11: 660 | I11: My cat loves watermelon, but she doesn't like cantaloupe. Op, if you are concerned about her being lonely, ask the cat distribution system to give you another baby from litter and go back to bush you found her at with a couple of cans of cat food. Thank you for rescuing her. If you decide not to keep her, please find a rescue or no kill shelter. Please don't give her away to anyone you don't know personally, there are a lot of people out there search for free animals to use or bait animals or will do other horrific things to them. | J11: https://old.reddit.com/r/cats/comments/1vf38ox/found_this_kitten_at_a_gas_station_and_trying_to/p1m5y02/ | K11: https://old.reddit.com/r/cats/comments/1vf38ox/found_this_kitten_at_a_gas_station_and_trying_to/
A12: r/cats | B12: t3_1vf38ox | C12: Found this kitten at a gas station and trying to decide what’s best for her. | D12: t1_p1n324i | E12: 0 | F12: Livid_Walrus7829 | G12: 46238.535 | H12: 620 | I12: Stop cause this looks exactly my baby when she was found at a gas station. Even the same collar. Shes a year now. <image> | J12: https://old.reddit.com/r/cats/comments/1vf38ox/found_this_kitten_at_a_gas_station_and_trying_to/p1n324i/ | K12: https://old.reddit.com/r/cats/comments/1vf38ox/found_this_kitten_at_a_gas_station_and_trying_to/
A13: r/cats | B13: t3_1vf38ox | C13: Found this kitten at a gas station and trying to decide what’s best for her. | D13: t1_p1lvfrq | E13: 0 | F13: Foreveralone84 | G13: 46238.322 | H13: 586 | I13: The only sensible suggestion... Up you go! | J13: https://old.reddit.com/r/cats/comments/1vf38ox/found_this_kitten_at_a_gas_station_and_trying_to/p1lvfrq/ | K13: https://old.reddit.com/r/cats/comments/1vf38ox/found_this_kitten_at_a_gas_station_and_trying_to/
... A29: r/cats | B29: t3_1vf38ox | C29: Found this kitten at a gas station and trying to decide what’s best for her. | D29: t1_p1mivnx | E29: 0 | F29: FunArtichoke8706 | G29: 46238.452 | H29: 195 | I29: But if you get more, try not to leave just one alone outside :( | J29: https://old.reddit.com/r/cats/comments/1vf38ox/found_this_kitten_at_a_gas_station_and_trying_to/p1mivnx/ | K29: https://old.reddit.com/r/cats/comments/1vf38ox/found_this_kitten_at_a_gas_station_and_trying_to/
A30: r/cats | B30: t3_1vf38ox | C30: Found this kitten at a gas station and trying to decide what’s best for her. | D30: t1_p1px7az | E30: 0 | F30: strong_systems | G30: 46238.842 | H30: 176 | J30: https://old.reddit.com/r/cats/comments/1vf38ox/found_this_kitten_at_a_gas_station_and_trying_to/p1px7az/ | K30: https://old.reddit.com/r/cats/comments/1vf38ox/found_this_kitten_at_a_gas_station_and_trying_to/
A31: r/cats | B31: t3_1vf38ox | C31: Found this kitten at a gas station and trying to decide what’s best for her. | D31: t1_p1qk29w | E31: 0 | F31: i_AM_A-ShArk | G31: 46238.914 | H31: 176 | I31: You put a collar on her, you’re not debating anything | J31: https://old.reddit.com/r/cats/comments/1vf38ox/found_this_kitten_at_a_gas_station_and_trying_to/p1qk29w/ | K31: https://old.reddit.com/r/cats/comments/1vf38ox/found_this_kitten_at_a_gas_station_and_trying_to/
A32: r/cats | B32: t3_1vf38ox | C32: Found this kitten at a gas station and trying to decide what’s best for her. | D32: t1_p1nt023 | E32: 0 | F32: madampc | G32: 46238.619 | H32: 175 | I32: The cat distribution system gave me this one, which also looks like yours <image> | J32: https://old.reddit.com/r/cats/comments/1vf38ox/found_this_kitten_at_a_gas_station_and_trying_to/p1nt023/ | K32: https://old.reddit.com/r/cats/comments/1vf38ox/found_this_kitten_at_a_gas_station_and_trying_to/
A33: r/cats | B33: t3_1vf38ox | C33: Found this kitten at a gas station and trying to decide what’s best for her. | D33: t1_p1mkr5t | E33: 0 | F33: early_birdy | G33: 46238.46 | H33: 143 | I33: You mean the cat dispensing system? | J33: https://old.reddit.com/r/cats/comments/1vf38ox/found_this_kitten_at_a_gas_station_and_trying_to/p1mkr5t/ | K33: https://old.reddit.com/r/cats/comments/1vf38ox/found_this_kitten_at_a_gas_station_and_trying_to/
A34: r/cats | B34: t3_1vf38ox | C34: Found this kitten at a gas station and trying to decide what’s best for her. | D34: t1_p1n792q | E34: 0 | F34: pandasareliars | G34: 46238.549 | H34: 137 | I34: Kittens are easier to raise in sets? I see what you're trying to do here and I like it. | J34: https://old.reddit.com/r/cats/comments/1vf38ox/found_this_kitten_at_a_gas_station_and_trying_to/p1n792q/ | K34: https://old.reddit.com/r/cats/comments/1vf38ox/found_this_kitten_at_a_gas_station_and_trying_to/
A35: r/cats | B35: t3_1vf38ox | C35: Found this kitten at a gas station and trying to decide what’s best for her. | D35: t1_p1m18ze | E35: 0 | F35: Cloaked42m | G35: 46238.355 | H35: 134 | I35: They always may prefer wet food but dry kibble is fine. Measure the dry food. If it says a half cup per day, split it between breakfast and dinner. If you share your dinner, teach her manners or she'll yank your sandwich out of your hand. Cats understand No at an early age. Just say No firmly and give her a firm tap on her forehead if she goes for your food. Priorities are shots and spayed. And yes, they are happiest with another cat. | J35: https://old.reddit.com/r/cats/comments/1vf38ox/found_this_kitten_at_a_gas_station_and_trying_to/p1m18ze/ | K35: https://old.reddit.com/r/cats/comments/1vf38ox/found_this_kitten_at_a_gas_station_and_trying_to/
A36: r/cats | B36: t3_1vf38ox | C36: Found this kitten at a gas station and trying to decide what’s best for her. | D36: t1_p1ncmcr | E36: 0 | F36: Semjaja | G36: 46238.567 | H36: 129 | I36: Definitely the right decision! | J36: https://old.reddit.com/r/cats/comments/1vf38ox/found_this_kitten_at_a_gas_station_and_trying_to/p1ncmcr/ | K36: https://old.reddit.com/r/cats/comments/1vf38ox/found_this_kitten_at_a_gas_station_and_trying_to/
A37: r/cats | B37: t3_1vf38ox | C37: Found this kitten at a gas station and trying to decide what’s best for her. | D37: t1_p1rijns | E37: 0 | F37: Ok-Scheme8634 | G37: 46239.037 | H37: 121 | I37: My boy when he was a kitten. The couch was a futon without arm rests so it reminded me of a therapist couch a little, and he reminds me of a teeny therapist waiting for you to get on the couch so he can listen while making biscuits in your intestines lol <image> | J37: https://old.reddit.com/r/cats/comments/1vf38ox/found_this_kitten_at_a_gas_station_and_trying_to/p1rijns/ | K37: https://old.reddit.com/r/cats/comments/1vf38ox/found_this_kitten_at_a_gas_station_and_trying_to/
A38: r/cats | B38: t3_1vf38ox | C38: Found this kitten at a gas station and trying to decide what’s best for her. | D38: t1_p1otr2x | E38: 0 | F38: Steadyandquick | G38: 46238.726 | H38: 117 | I38: Yes! She was in a bush in a gas station! You saved her from getting hit by a car or worse. You could always return to said bush and bring home a sibling! They would tire each other out and be grateful. You are a great human! | J38: https://old.reddit.com/r/cats/comments/1vf38ox/found_this_kitten_at_a_gas_station_and_trying_to/p1otr2x/ | K38: https://old.reddit.com/r/cats/comments/1vf38ox/found_this_kitten_at_a_gas_station_and_trying_to/
A39: r/cats | B39: t3_1vf38ox | C39: Found this kitten at a gas station and trying to decide what’s best for her. | D39: t1_p1m2ktz | E39: 0 | F39: Zherneb | G39: 46238.363 | H39: 116 | I39: Then a third cat so when they fight, they have someone else to cuddle with. Then a forth so there is no cat ever alone when any argue! Then a fifth because it's cute and fluffy! | J39: https://old.reddit.com/r/cats/comments/1vf38ox/found_this_kitten_at_a_gas_station_and_trying_to/p1m2ktz/ | K39: https://old.reddit.com/r/cats/comments/1vf38ox/found_this_kitten_at_a_gas_station_and_trying_to/
A40: r/cats | B40: t3_1vf38ox | C40: Found this kitten at a gas station and trying to decide what’s best for her. | D40: t1_p1niz7s | E40: 0 | F40: Oykatet | G40: 46238.588 | H40: 107 | I40: I hope they see this comment because that would just be heartbreaking. They should grab them all and keep 2 and find homes for the others. How can they be absolutely sure they aren't leaving one behind though? | J40: https://old.reddit.com/r/cats/comments/1vf38ox/found_this_kitten_at_a_gas_station_and_trying_to/p1niz7s/ | K40: https://old.reddit.com/r/cats/comments/1vf38ox/found_this_kitten_at_a_gas_station_and_trying_to/
A41: r/cats | B41: t3_1vf38ox | C41: Found this kitten at a gas station and trying to decide what’s best for her. | D41: t1_p1nc8cp | E41: 0 | F41: Sveitsinvaltaaja | G41: 46238.566 | H41: 94 | I41: My cat loved honeydew <image> | J41: https://old.reddit.com/r/cats/comments/1vf38ox/found_this_kitten_at_a_gas_station_and_trying_to/p1nc8cp/ | K41: https://old.reddit.com/r/cats/comments/1vf38ox/found_this_kitten_at_a_gas_station_and_trying_to/
A42: r/cats | B42: t3_1vf38ox | C42: Found this kitten at a gas station and trying to decide what’s best for her. | D42: t1_p1mithp | E42: 0 | F42: Crazy_Opposite_4264 | G42: 46238.451 | H42: 94 | I42: She already looks like she belongs there and it's honestly hard not to smile at that. | J42: https://old.reddit.com/r/cats/comments/1vf38ox/found_this_kitten_at_a_gas_station_and_trying_to/p1mithp/ | K42: https://old.reddit.com/r/cats/comments/1vf38ox/found_this_kitten_at_a_gas_station_and_trying_to/
... A45: r/cats | B45: t3_1vf38ox | C45: Found this kitten at a gas station and trying to decide what’s best for her. | D45: t1_p1p1blf | E45: 0 | F45: Shattingpancreas_ | G45: 46238.748 | H45: 86 | I45: <image> I also found a cat last week. The vet thinks she’s about four months old. | J45: https://old.reddit.com/r/cats/comments/1vf38ox/found_this_kitten_at_a_gas_station_and_trying_to/p1p1blf/ | K45: https://old.reddit.com/r/cats/comments/1vf38ox/found_this_kitten_at_a_gas_station_and_trying_to/
A46: r/cats | B46: t3_1vf38ox | C46: Found this kitten at a gas station and trying to decide what’s best for her. | D46: t1_p1ov1sz | E46: 0 | F46: FunkyInclination | G46: 46238.73 | H46: 85 | J46: https://old.reddit.com/r/cats/comments/1vf38ox/found_this_kitten_at_a_gas_station_and_trying_to/p1ov1sz/ | K46: https://old.reddit.com/r/cats/comments/1vf38ox/found_this_kitten_at_a_gas_station_and_trying_to/
A47: r/cats | B47: t3_1vf38ox | C47: Found this kitten at a gas station and trying to decide what’s best for her. | D47: t1_p1n0w8v | E47: 0 | F47: WenDeckerstArt | G47: 46238.527 | H47: 85 | I47: You put a collar on her? She’s yours now!! Congratulations!!! | J47: https://old.reddit.com/r/cats/comments/1vf38ox/found_this_kitten_at_a_gas_station_and_trying_to/p1n0w8v/ | K47: https://old.reddit.com/r/cats/comments/1vf38ox/found_this_kitten_at_a_gas_station_and_trying_to/
A48: r/cats | B48: t3_1vf38ox | C48: Found this kitten at a gas station and trying to decide what’s best for her. | D48: t1_p1ms6u2 | E48: 0 | F48: dancingpianofairy | G48: 46238.493 | H48: 83 | I48: OP mentioned the others skedaddled. The only reason they got this one was because she stayed. | J48: https://old.reddit.com/r/cats/comments/1vf38ox/found_this_kitten_at_a_gas_station_and_trying_to/p1ms6u2/ | K48: https://old.reddit.com/r/cats/comments/1vf38ox/found_this_kitten_at_a_gas_station_and_trying_to/
A49: r/cats | B49: t3_1vf38ox | C49: Found this kitten at a gas station and trying to decide what’s best for her. | D49: t1_p1n5tcz | E49: 0 | F49: Queasy-Celery-7982 | G49: 46238.544 | H49: 81 | I49: All of my animals I get in pairs for this reason. :) | J49: https://old.reddit.com/r/cats/comments/1vf38ox/found_this_kitten_at_a_gas_station_and_trying_to/p1n5tcz/ | K49: https://old.reddit.com/r/cats/comments/1vf38ox/found_this_kitten_at_a_gas_station_and_trying_to/
A50: r/cats | B50: t3_1vf38ox | C50: Found this kitten at a gas station and trying to decide what’s best for her. | D50: t1_p1ndsip | E50: 0 | F50: Serious-Tiger734 | G50: 46238.571 | H50: 74 | I50: I prefer in triplets. This helps when one cat is moody and wants to be left alone. This lets the other two cuddle. On those days when everyone is happy they can form a puddle. It always seems one of them is moody on any given day | J50: https://old.reddit.com/r/cats/comments/1vf38ox/found_this_kitten_at_a_gas_station_and_trying_to/p1ndsip/ | K50: https://old.reddit.com/r/cats/comments/1vf38ox/found_this_kitten_at_a_gas_station_and_trying_to/
A51: r/cats | B51: t3_1vf38ox | C51: Found this kitten at a gas station and trying to decide what’s best for her. | D51: t1_p1lukmh | E51: 0 | F51: KeeKyieTheMorris | G51: 46238.316 | H51: 70 | I51: 😍 oh my gah She is such a cutie pie. Is it possible to try to find the other kitties? I’m not an expert but every cat is different so it’s hard to know if she’ll be lonely or not later on when she’s older | J51: https://old.reddit.com/r/cats/comments/1vf38ox/found_this_kitten_at_a_gas_station_and_trying_to/p1lukmh/ | K51: https://old.reddit.com/r/cats/comments/1vf38ox/found_this_kitten_at_a_gas_station_and_trying_to/
A52: r/cats | B52: t3_1vf38ox | C52: Found this kitten at a gas station and trying to decide what’s best for her. | D52: t1_p1mmcbd | E52: 0 | F52: ericlikesyou | G52: 46238.468 | H52: 68 | I52: im glad someone else is saying this, not really a CDS situation imo | J52: https://old.reddit.com/r/cats/comments/1vf38ox/found_this_kitten_at_a_gas_station_and_trying_to/p1mmcbd/ | K52: https://old.reddit.com/r/cats/comments/1vf38ox/found_this_kitten_at_a_gas_station_and_trying_to/
A53: r/cats | B53: t3_1vf38ox | C53: Found this kitten at a gas station and trying to decide what’s best for her. | D53: t1_p1n062c | E53: 0 | F53: LevelPerception4 | G53: 46238.524 | H53: 67 | I53: Much, much easier! They will entertain and be company for each other while you’re at work. | J53: https://old.reddit.com/r/cats/comments/1vf38ox/found_this_kitten_at_a_gas_station_and_trying_to/p1n062c/ | K53: https://old.reddit.com/r/cats/comments/1vf38ox/found_this_kitten_at_a_gas_station_and_trying_to/
A54: r/cats | B54: t3_1vf38ox | C54: Found this kitten at a gas station and trying to decide what’s best for her. | D54: t1_p1s14oh | E54: 0 | F54: abroberts1 | G54: 46239.108 | H54: 65 | I54: That looks like a stock photo 😂 | J54: https://old.reddit.com/r/cats/comments/1vf38ox/found_this_kitten_at_a_gas_station_and_trying_to/p1s14oh/ | K54: https://old.reddit.com/r/cats/comments/1vf38ox/found_this_kitten_at_a_gas_station_and_trying_to/
A55: r/cats | B55: t3_1vf38ox | C55: Found this kitten at a gas station and trying to decide what’s best for her. | D55: t1_p1lx1q2 | E55: 0 | F55: Saudade_Daddy | G55: 46238.331 | H55: 65 | I55: I did happen to stop by earlier today before I got home but I didn’t hear or see them. I think they set up their home behind the gas station where they keep the dumpsters in a fenced area, which is locked. Not 100% sure but if I was a momma cat with babies I’d set up shop right there. | J55: https://old.reddit.com/r/cats/comments/1vf38ox/found_this_kitten_at_a_gas_station_and_trying_to/p1lx1q2/ | K55: https://old.reddit.com/r/cats/comments/1vf38ox/found_this_kitten_at_a_gas_station_and_trying_to/
A56: r/cats | B56: t3_1vf38ox | C56: Found this kitten at a gas station and trying to decide what’s best for her. | D56: t1_p1otj0g | E56: 0 | F56: Queasy-Celery-7982 | G56: 46238.726 | H56: 62 | I56: PS, I have two cats, two dogs, two guinea pigs, two fish. I only strayed from this rule with 3 daughters and one husband. :) | J56: https://old.reddit.com/r/cats/comments/1vf38ox/found_this_kitten_at_a_gas_station_and_trying_to/p1otj0g/ | K56: https://old.reddit.com/r/cats/comments/1vf38ox/found_this_kitten_at_a_gas_station_and_trying_to/
A57: r/cats | B57: t3_1vf38ox | C57: Found this kitten at a gas station and trying to decide what’s best for her. | D57: t1_p1nyipv | E57: 0 | F57: ggt3416 | G57: 46238.635 | H57: 62 | I57: Honestly OP, this is sound advice. Kittens are amazing in pairs. If you can go back and grab one of the other gas station bush baby, that would be best. They will keep each other company and I promise taking care of 2 is easier than it seems. | J57: https://old.reddit.com/r/cats/comments/1vf38ox/found_this_kitten_at_a_gas_station_and_trying_to/p1nyipv/ | K57: https://old.reddit.com/r/cats/comments/1vf38ox/found_this_kitten_at_a_gas_station_and_trying_to/
A58: r/cats | B58: t3_1vf38ox | C58: Found this kitten at a gas station and trying to decide what’s best for her. | D58: t1_p1m40jm | E58: 0 | F58: literally_lemons | G58: 46238.371 | H58: 60 | I58: Ahahaha I love this | J58: https://old.reddit.com/r/cats/comments/1vf38ox/found_this_kitten_at_a_gas_station_and_trying_to/p1m40jm/ | K58: https://old.reddit.com/r/cats/comments/1vf38ox/found_this_kitten_at_a_gas_station_and_trying_to/
... A160: r/cats | B160: t3_1vf38ox | C160: Found this kitten at a gas station and trying to decide what’s best for her. | D160: t1_p1mhzg7 | E160: 0 | F160: Valkyriesride1 | G160: 46238.447 | H160: 11 | I160: Thank you for the award! | J160: https://old.reddit.com/r/cats/comments/1vf38ox/found_this_kitten_at_a_gas_station_and_trying_to/p1mhzg7/ | K160: https://old.reddit.com/r/cats/comments/1vf38ox/found_this_kitten_at_a_gas_station_and_trying_to/
A161: r/cats | B161: t3_1vf38ox | C161: Found this kitten at a gas station and trying to decide what’s best for her. | D161: t1_p1mxs8s | E161: 0 | F161: Evening-Reach-4281 | G161: 46238.515 | H161: 11 | J161: https://old.reddit.com/r/cats/comments/1vf38ox/found_this_kitten_at_a_gas_station_and_trying_to/p1mxs8s/ | K161: https://old.reddit.com/r/cats/comments/1vf38ox/found_this_kitten_at_a_gas_station_and_trying_to/
A162: r/cats | B162: t3_1vf38ox | C162: Found this kitten at a gas station and trying to decide what’s best for her. | D162: t1_p1mly95 | E162: 0 | F162: Killer_Lichen | G162: 46238.466 | H162: 11 | I162: Marina Raskova, led an all women bomber squadron for the Soviet Union in WW2. Purrfect name for her if you ask me | J162: https://old.reddit.com/r/cats/comments/1vf38ox/found_this_kitten_at_a_gas_station_and_trying_to/p1mly95/ | K162: https://old.reddit.com/r/cats/comments/1vf38ox/found_this_kitten_at_a_gas_station_and_trying_to/
A163: r/cats | B163: t3_1vf38ox | C163: Found this kitten at a gas station and trying to decide what’s best for her. | D163: t1_p1mcr3z | E163: 0 | F163: PJKPJT7915 | G163: 46238.421 | H163: 10 | I163: I've had cats that love watermelon and cantaloupe. | J163: https://old.reddit.com/r/cats/comments/1vf38ox/found_this_kitten_at_a_gas_station_and_trying_to/p1mcr3z/ | K163: https://old.reddit.com/r/cats/comments/1vf38ox/found_this_kitten_at_a_gas_station_and_trying_to/
A164: r/cats | B164: t3_1vf38ox | C164: Found this kitten at a gas station and trying to decide what’s best for her. | D164: t1_p1mvr84 | E164: 0 | F164: TheRebelSith | G164: 46238.507 | H164: 10 | I164: Now you're talkin | J164: https://old.reddit.com/r/cats/comments/1vf38ox/found_this_kitten_at_a_gas_station_and_trying_to/p1mvr84/ | K164: https://old.reddit.com/r/cats/comments/1vf38ox/found_this_kitten_at_a_gas_station_and_trying_to/
A165: r/cats | B165: t3_1vf38ox | C165: Found this kitten at a gas station and trying to decide what’s best for her. | D165: t1_p1lv0au | E165: 0 | F165: Apprehensive-Bit1634 | G165: 46238.319 | H165: 10 | I165: The CDS, with its advanced technology, has decided that you are the best thing for her. | J165: https://old.reddit.com/r/cats/comments/1vf38ox/found_this_kitten_at_a_gas_station_and_trying_to/p1lv0au/ | K165: https://old.reddit.com/r/cats/comments/1vf38ox/found_this_kitten_at_a_gas_station_and_trying_to/
A166: r/cats | B166: t3_1vf38ox | C166: Found this kitten at a gas station and trying to decide what’s best for her. | D166: t1_p1lwo8j | E166: 0 | F166: throwawabcintrovert | G166: 46238.329 | H166: 10 | I166: Enjoy your new sweetie. We found a black kitten that looks exactly like yours under some furniture outside our house. I set her up in a kennel while I decided which shelter she was going to go to because there's about 4 near me. My dad texted me a few minutes later and said "she's so pretty and relaxed. I'm taking her out to my office" So now we have another cat named Esmerelda lmao | J166: https://old.reddit.com/r/cats/comments/1vf38ox/found_this_kitten_at_a_gas_station_and_trying_to/p1lwo8j/ | K166: https://old.reddit.com/r/cats/comments/1vf38ox/found_this_kitten_at_a_gas_station_and_trying_to/
A167: r/cats | B167: t3_1vf38ox | C167: Found this kitten at a gas station and trying to decide what’s best for her. | D167: t1_p1qjvlt | E167: 0 | F167: Huge-Guitar1692 | G167: 46238.913 | H167: 10 | I167: Clearly a keeper. Keep that baby | J167: https://old.reddit.com/r/cats/comments/1vf38ox/found_this_kitten_at_a_gas_station_and_trying_to/p1qjvlt/ | K167: https://old.reddit.com/r/cats/comments/1vf38ox/found_this_kitten_at_a_gas_station_and_trying_to/
A168: r/cats | B168: t3_1vf38ox | C168: Found this kitten at a gas station and trying to decide what’s best for her. | D168: t1_p1p5ied | E168: 0 | F168: bendurrhover | G168: 46238.76 | H168: 9 | I168: Makes sense to me! | J168: https://old.reddit.com/r/cats/comments/1vf38ox/found_this_kitten_at_a_gas_station_and_trying_to/p1p5ied/ | K168: https://old.reddit.com/r/cats/comments/1vf38ox/found_this_kitten_at_a_gas_station_and_trying_to/
A169: r/cats | B169: t3_1vf38ox | C169: Found this kitten at a gas station and trying to decide what’s best for her. | D169: t1_p1okot3 | E169: 0 | F169: NECalifornian25 | G169: 46238.7 | H169: 9 | I169: I have a solo cat I got as a kitten, thank god my roommate had two young cats. The first couple of weeks they were separated until my boy had all his vaccines, and I was exhausted from all the kitten energy. It was also during Covid so I worked from home, he was very distracting lol. Just as an aside, he’s happiest now as an only cat. He does get bored at times, but he has an anxiety and seizure disorder so it’s better for him to be bored than overstimulated. He’s also very much a mama’s boy and would not want to share me, he already gets jealous of my laptop when I’m working from home 😂 | J169: https://old.reddit.com/r/cats/comments/1vf38ox/found_this_kitten_at_a_gas_station_and_trying_to/p1okot3/ | K169: https://old.reddit.com/r/cats/comments/1vf38ox/found_this_kitten_at_a_gas_station_and_trying_to/
A170: r/cats | B170: t3_1vf38ox | C170: Found this kitten at a gas station and trying to decide what’s best for her. | D170: t1_p1nl9we | E170: 0 | F170: MoonDragon59 | G170: 46238.595 | H170: 9 | I170: This is the way! 2 kittens keep each other company and entertained! | J170: https://old.reddit.com/r/cats/comments/1vf38ox/found_this_kitten_at_a_gas_station_and_trying_to/p1nl9we/ | K170: https://old.reddit.com/r/cats/comments/1vf38ox/found_this_kitten_at_a_gas_station_and_trying_to/
A171: r/cats | B171: t3_1vf38ox | C171: Found this kitten at a gas station and trying to decide what’s best for her. | D171: t1_p1oqk67 | E171: 0 | F171: n_daughter | G171: 46238.717 | H171: 9 | I171: This is so true. And they entertain each other! They learn not to bite because they see how it feels. So it keeps playing safe because they learn their limits. Except for the added cost of two, my family and I only saw benefits to getting 2 kittens. | J171: https://old.reddit.com/r/cats/comments/1vf38ox/found_this_kitten_at_a_gas_station_and_trying_to/p1oqk67/ | K171: https://old.reddit.com/r/cats/comments/1vf38ox/found_this_kitten_at_a_gas_station_and_trying_to/
A172: r/cats | B172: t3_1vf38ox | C172: Found this kitten at a gas station and trying to decide what’s best for her. | D172: t1_p1mw52b | E172: 0 | F172: natd327 | G172: 46238.509 | H172: 9 | I172: Why are they like this?? I’ve tried feeding her high quality food and even making her steak and salmon, and she only likes Purina cat food and every once in a while some boiled and shredded chicken. | J172: https://old.reddit.com/r/cats/comments/1vf38ox/found_this_kitten_at_a_gas_station_and_trying_to/p1mw52b/ | K172: https://old.reddit.com/r/cats/comments/1vf38ox/found_this_kitten_at_a_gas_station_and_trying_to/
A173: r/cats | B173: t3_1vf38ox | C173: Found this kitten at a gas station and trying to decide what’s best for her. | D173: t1_p1m8252 | E173: 0 | F173: QuietlySeething | G173: 46238.395 | H173: 9 | I173: I taught mine "last bite." If we have guests, they'll hold off on begging and just wait patiently if they're promised the last bite | J173: https://old.reddit.com/r/cats/comments/1vf38ox/found_this_kitten_at_a_gas_station_and_trying_to/p1m8252/ | K173: https://old.reddit.com/r/cats/comments/1vf38ox/found_this_kitten_at_a_gas_station_and_trying_to/
... A207: r/cats | B207: t3_1vf38ox | C207: Found this kitten at a gas station and trying to decide what’s best for her. | D207: t1_p1nv3d2 | E207: 0 | F207: princessjemmy | G207: 46238.625 | H207: 5 | I207: 🤣 | J207: https://old.reddit.com/r/cats/comments/1vf38ox/found_this_kitten_at_a_gas_station_and_trying_to/p1nv3d2/ | K207: https://old.reddit.com/r/cats/comments/1vf38ox/found_this_kitten_at_a_gas_station_and_trying_to/
A208: r/cats | B208: t3_1vf38ox | C208: Found this kitten at a gas station and trying to decide what’s best for her. | E208: 0 | G208: 46238.354 | H208: 5 | I208: [removed] | J208: https://old.reddit.com/r/cats/comments/1vf38ox/found_this_kitten_at_a_gas_station_and_trying_to/p1mahnh/ | K208: https://old.reddit.com/r/cats/comments/1vf38ox/found_this_kitten_at_a_gas_station_and_trying_to/
A209: r/cats | B209: t3_1vf38ox | C209: Found this kitten at a gas station and trying to decide what’s best for her. | D209: t1_p1mahnh | E209: 0 | F209: ILoveKittyPoo | G209: 46238.408 | H209: 5 | I209: Agreed! We kept two babies together as litter mates and they are so much less of terror balls of energy than single kittens. Also kept my 6 yr old from bullying the 11 yr old because they keep him so busy. | J209: https://old.reddit.com/r/cats/comments/1vf38ox/found_this_kitten_at_a_gas_station_and_trying_to/p1mahnh/ | K209: https://old.reddit.com/r/cats/comments/1vf38ox/found_this_kitten_at_a_gas_station_and_trying_to/
A210: r/cats | B210: t3_1vf38ox | C210: Found this kitten at a gas station and trying to decide what’s best for her. | D210: t1_p1mie02 | E210: 0 | F210: Dazey13 | G210: 46238.449 | H210: 5 | I210: I don't know why anyone would down vote, she clearly is very politely asking for fruits plz and thank you. 🍓 | J210: https://old.reddit.com/r/cats/comments/1vf38ox/found_this_kitten_at_a_gas_station_and_trying_to/p1mie02/ | K210: https://old.reddit.com/r/cats/comments/1vf38ox/found_this_kitten_at_a_gas_station_and_trying_to/
A211: r/cats | B211: t3_1vf38ox | C211: Found this kitten at a gas station and trying to decide what’s best for her. | D211: t1_p1m7iq2 | E211: 0 | F211: LIJRD1 | G211: 46238.392 | H211: 5 | I211: You have your answer. You subconsciously have chosen when you rescued her and now named her. Shes your new housemate. Can you imagine not having her already? | J211: https://old.reddit.com/r/cats/comments/1vf38ox/found_this_kitten_at_a_gas_station_and_trying_to/p1m7iq2/ | K211: https://old.reddit.com/r/cats/comments/1vf38ox/found_this_kitten_at_a_gas_station_and_trying_to/
A212: r/cats | B212: t3_1vf38ox | C212: Found this kitten at a gas station and trying to decide what’s best for her. | D212: t1_p1m91mn | E212: 0 | F212: trippsalot_ | G212: 46238.4 | H212: 5 | I212: She’s like “youre my human now right ?” Look at that face dont take her to a shelter yall chose each other | J212: https://old.reddit.com/r/cats/comments/1vf38ox/found_this_kitten_at_a_gas_station_and_trying_to/p1m91mn/ | K212: https://old.reddit.com/r/cats/comments/1vf38ox/found_this_kitten_at_a_gas_station_and_trying_to/
A213: r/cats | B213: t3_1vf38ox | C213: Found this kitten at a gas station and trying to decide what’s best for her. | D213: t1_p1m9m63 | E213: 0 | F213: ManatuBear | G213: 46238.404 | H213: 5 | I213: Cats don't need much company. I'm home all day and my cat only remembers I exist when it's feeding time and for a 1 hour cuddle before bedtime. She has her own routine during the day, like lounging in a chair in the morning, then sunbathing in the backyard in the afternoon. | J213: https://old.reddit.com/r/cats/comments/1vf38ox/found_this_kitten_at_a_gas_station_and_trying_to/p1m9m63/ | K213: https://old.reddit.com/r/cats/comments/1vf38ox/found_this_kitten_at_a_gas_station_and_trying_to/
A214: r/cats | B214: t3_1vf38ox | C214: Found this kitten at a gas station and trying to decide what’s best for her. | D214: t1_p1mo0gd | E214: 0 | F214: No-Fish9282 | G214: 46238.475 | H214: 5 | I214: Please go back to the gas station and see if you can find her mum ( who is probably fretting) and her siblings. If you can catch them all, take them all to a shelter, where this kitten and her family can all be together. Let the shelter help this little cat family, and give them your details to adopt this one. Her mum is probably looking for her, kindest to check. If you can't find them, please go to the nearest shelter and let them know. The rest of the family may have been rescued already. Thank you for your compassion. | J214: https://old.reddit.com/r/cats/comments/1vf38ox/found_this_kitten_at_a_gas_station_and_trying_to/p1mo0gd/ | K214: https://old.reddit.com/r/cats/comments/1vf38ox/found_this_kitten_at_a_gas_station_and_trying_to/
A215: r/cats | B215: t3_1vf38ox | C215: Found this kitten at a gas station and trying to decide what’s best for her. | D215: t1_p1of0vp | E215: 0 | F215: nanacmm | G215: 46238.684 | H215: 5 | I215: You go back and get the other kitties. Loneliness problem solved | J215: https://old.reddit.com/r/cats/comments/1vf38ox/found_this_kitten_at_a_gas_station_and_trying_to/p1of0vp/ | K215: https://old.reddit.com/r/cats/comments/1vf38ox/found_this_kitten_at_a_gas_station_and_trying_to/
A216: r/cats | B216: t3_1vf38ox | C216: Found this kitten at a gas station and trying to decide what’s best for her. | D216: t1_p1lwu4a | E216: 0 | F216: weedlemethis | G216: 46238.33 | H216: 5 | I216: Looks like you need to go back to the same place and get a second kitten for her and even better it would be a sibling | J216: https://old.reddit.com/r/cats/comments/1vf38ox/found_this_kitten_at_a_gas_station_and_trying_to/p1lwu4a/ | K216: https://old.reddit.com/r/cats/comments/1vf38ox/found_this_kitten_at_a_gas_station_and_trying_to/
A217: r/cats | B217: t3_1vf38ox | C217: Found this kitten at a gas station and trying to decide what’s best for her. | D217: t1_p1m068c | E217: 0 | F217: Overall-Honeydew2038 | G217: 46238.349 | H217: 5 | I217: Looks like she’s made herself home… you have no choice 💀😂 | J217: https://old.reddit.com/r/cats/comments/1vf38ox/found_this_kitten_at_a_gas_station_and_trying_to/p1m068c/ | K217: https://old.reddit.com/r/cats/comments/1vf38ox/found_this_kitten_at_a_gas_station_and_trying_to/
A218: r/cats | B218: t3_1vf38ox | C218: Found this kitten at a gas station and trying to decide what’s best for her. | D218: t1_p1mb3u3 | E218: 0 | F218: Dustband1t | G218: 46238.412 | H218: 5 | I218: Cat probably “I require sustenance human!” | J218: https://old.reddit.com/r/cats/comments/1vf38ox/found_this_kitten_at_a_gas_station_and_trying_to/p1mb3u3/ | K218: https://old.reddit.com/r/cats/comments/1vf38ox/found_this_kitten_at_a_gas_station_and_trying_to/
A219: r/cats | B219: t3_1vf38ox | C219: Found this kitten at a gas station and trying to decide what’s best for her. | D219: t1_p1mbbvr | E219: 0 | F219: SuperSourSkittles | G219: 46238.413 | H219: 5 | I219: We have a cat that would come around, she would see our other cats on our cat patio (huge space, enclosed with lattice with cat doors going inside the house, they’re spoiled) and she decided she wanted to live there too. We took her in and named her Misty, she’s a black kitty too. Sweetest little cat ever! She had enough of being a stray I guess. But OP, you have been chosen. She will be happy with you. | J219: https://old.reddit.com/r/cats/comments/1vf38ox/found_this_kitten_at_a_gas_station_and_trying_to/p1mbbvr/ | K219: https://old.reddit.com/r/cats/comments/1vf38ox/found_this_kitten_at_a_gas_station_and_trying_to/
A220: r/cats | B220: t3_1vf38ox | C220: Found this kitten at a gas station and trying to decide what’s best for her. | D220: t1_p1mj23u | E220: 0 | F220: Iexistya | G220: 46238.452 | H220: 5 | I220: the void needs thy conpany, accept your fate | J220: https://old.reddit.com/r/cats/comments/1vf38ox/found_this_kitten_at_a_gas_station_and_trying_to/p1mj23u/ | K220: https://old.reddit.com/r/cats/comments/1vf38ox/found_this_kitten_at_a_gas_station_and_trying_to/
... A306: r/cats | B306: t3_1vf38ox | C306: Found this kitten at a gas station and trying to decide what’s best for her. | D306: t1_p1lt9n7 | E306: 0 | F306: vwinterfawn | G306: 46238.309 | H306: 3 | I306: 🥭 | J306: https://old.reddit.com/r/cats/comments/1vf38ox/found_this_kitten_at_a_gas_station_and_trying_to/p1lt9n7/ | K306: https://old.reddit.com/r/cats/comments/1vf38ox/found_this_kitten_at_a_gas_station_and_trying_to/
A307: r/cats | B307: t3_1vf38ox | C307: Found this kitten at a gas station and trying to decide what’s best for her. | D307: t1_p1m48ki | E307: 0 | F307: StageAboveWater | G307: 46238.373 | H307: 3 | J307: https://old.reddit.com/r/cats/comments/1vf38ox/found_this_kitten_at_a_gas_station_and_trying_to/p1m48ki/ | K307: https://old.reddit.com/r/cats/comments/1vf38ox/found_this_kitten_at_a_gas_station_and_trying_to/
A308: r/cats | B308: t3_1vf38ox | C308: Found this kitten at a gas station and trying to decide what’s best for her. | D308: t1_p1mib1h | E308: 0 | F308: blah_2520 | G308: 46238.449 | H308: 3 | I308: The best for her is for you to accept thah you have been adopted.. cats are more I independent than dogs, as long as you leave food and their place to poop they’ll be fine and you’ll be happier coming home | J308: https://old.reddit.com/r/cats/comments/1vf38ox/found_this_kitten_at_a_gas_station_and_trying_to/p1mib1h/ | K308: https://old.reddit.com/r/cats/comments/1vf38ox/found_this_kitten_at_a_gas_station_and_trying_to/
A309: r/cats | B309: t3_1vf38ox | C309: Found this kitten at a gas station and trying to decide what’s best for her. | D309: t1_p1mrdeh | E309: 0 | F309: Aromatic-sparkles | G309: 46238.489 | H309: 3 | I309: If you can handle two, go back and try to get one of her littermates. They’ll both be better off, happier, and will keep each other company. The shelter told me “they go together or they don’t go” when I got my two (brothers from another mother…) and it has been the BEST!! | J309: https://old.reddit.com/r/cats/comments/1vf38ox/found_this_kitten_at_a_gas_station_and_trying_to/p1mrdeh/ | K309: https://old.reddit.com/r/cats/comments/1vf38ox/found_this_kitten_at_a_gas_station_and_trying_to/
A310: r/cats | B310: t3_1vf38ox | C310: Found this kitten at a gas station and trying to decide what’s best for her. | D310: t1_p1mzuu5 | E310: 0 | F310: MushroomPitiful9280 | G310: 46238.523 | H310: 3 | I310: Looks like YOU are whats best for her. And why not call her Lucky Lefty.. bc she got left behind by her littermates, and lucky she found you.. | J310: https://old.reddit.com/r/cats/comments/1vf38ox/found_this_kitten_at_a_gas_station_and_trying_to/p1mzuu5/ | K310: https://old.reddit.com/r/cats/comments/1vf38ox/found_this_kitten_at_a_gas_station_and_trying_to/
A311: r/cats | B311: t3_1vf38ox | C311: Found this kitten at a gas station and trying to decide what’s best for her. | D311: t1_p1o5biy | E311: 0 | F311: blueevey | G311: 46238.656 | H311: 3 | I311: Princess Kate! Go back to the gas station and look for the other kitties. Keep two, or however many are necessary to keep pairs together. | J311: https://old.reddit.com/r/cats/comments/1vf38ox/found_this_kitten_at_a_gas_station_and_trying_to/p1o5biy/ | K311: https://old.reddit.com/r/cats/comments/1vf38ox/found_this_kitten_at_a_gas_station_and_trying_to/
A312: r/cats | B312: t3_1vf38ox | C312: Found this kitten at a gas station and trying to decide what’s best for her. | D312: t1_p1p4r2f | E312: 0 | F312: dreamatoriumx | G312: 46238.758 | H312: 3 | I312: You have been Issued (1) Void. -the Universe | J312: https://old.reddit.com/r/cats/comments/1vf38ox/found_this_kitten_at_a_gas_station_and_trying_to/p1p4r2f/ | K312: https://old.reddit.com/r/cats/comments/1vf38ox/found_this_kitten_at_a_gas_station_and_trying_to/
A313: r/cats | B313: t3_1vf38ox | C313: Found this kitten at a gas station and trying to decide what’s best for her. | D313: t1_p1lwqzy | E313: 0 | F313: ilikequestions172 | G313: 46238.329 | H313: 3 | I313: Give it the wrong fruit and your life is over | J313: https://old.reddit.com/r/cats/comments/1vf38ox/found_this_kitten_at_a_gas_station_and_trying_to/p1lwqzy/ | K313: https://old.reddit.com/r/cats/comments/1vf38ox/found_this_kitten_at_a_gas_station_and_trying_to/
A314: r/cats | B314: t3_1vf38ox | C314: Found this kitten at a gas station and trying to decide what’s best for her. | D314: t1_p1lwu0u | E314: 0 | F314: LemonOld8150 | G314: 46238.33 | H314: 3 | I314: Go get another of the kittens for a buddy Plz call a cat rescue and tell them where the kittens are . Hopefully you could take some food and water by for them till someone can pick them up | J314: https://old.reddit.com/r/cats/comments/1vf38ox/found_this_kitten_at_a_gas_station_and_trying_to/p1lwu0u/ | K314: https://old.reddit.com/r/cats/comments/1vf38ox/found_this_kitten_at_a_gas_station_and_trying_to/
A315: r/cats | B315: t3_1vf38ox | C315: Found this kitten at a gas station and trying to decide what’s best for her. | D315: t1_p1ly329 | E315: 0 | F315: Illustrious-Air-1681 | G315: 46238.337 | H315: 3 | I315: Loving home and plenty of fruit. You will have a wonderful life together. | J315: https://old.reddit.com/r/cats/comments/1vf38ox/found_this_kitten_at_a_gas_station_and_trying_to/p1ly329/ | K315: https://old.reddit.com/r/cats/comments/1vf38ox/found_this_kitten_at_a_gas_station_and_trying_to/
A316: r/cats | B316: t3_1vf38ox | C316: Found this kitten at a gas station and trying to decide what’s best for her. | D316: t1_p1lya4m | E316: 0 | F316: emorrigan | G316: 46238.338 | H316: 3 | I316: Get her a playmate or two! They really do keep each other company (and out of trouble)! | J316: https://old.reddit.com/r/cats/comments/1vf38ox/found_this_kitten_at_a_gas_station_and_trying_to/p1lya4m/ | K316: https://old.reddit.com/r/cats/comments/1vf38ox/found_this_kitten_at_a_gas_station_and_trying_to/
A317: r/cats | B317: t3_1vf38ox | C317: Found this kitten at a gas station and trying to decide what’s best for her. | D317: t1_p1lyakq | E317: 0 | F317: temp__text | G317: 46238.338 | H317: 3 | I317: Shelters can be stressful for kitties. If you can spend more time, keeping her would be a wonderful choice for both of you. | J317: https://old.reddit.com/r/cats/comments/1vf38ox/found_this_kitten_at_a_gas_station_and_trying_to/p1lyakq/ | K317: https://old.reddit.com/r/cats/comments/1vf38ox/found_this_kitten_at_a_gas_station_and_trying_to/
A318: r/cats | B318: t3_1vf38ox | C318: Found this kitten at a gas station and trying to decide what’s best for her. | D318: t1_p1lyaw0 | E318: 0 | F318: FatCat_13 | G318: 46238.338 | H318: 3 | I318: Go back to where you found her. Take home all her sibling. Et voilà! She won’t be lonely when you’re out. | J318: https://old.reddit.com/r/cats/comments/1vf38ox/found_this_kitten_at_a_gas_station_and_trying_to/p1lyaw0/ | K318: https://old.reddit.com/r/cats/comments/1vf38ox/found_this_kitten_at_a_gas_station_and_trying_to/
A319: r/cats | B319: t3_1vf38ox | C319: Found this kitten at a gas station and trying to decide what’s best for her. | D319: t1_p1lywb1 | E319: 0 | F319: Murky-Eggplant650 | G319: 46238.342 | H319: 3 | I319: Thats one adorable kitten! | J319: https://old.reddit.com/r/cats/comments/1vf38ox/found_this_kitten_at_a_gas_station_and_trying_to/p1lywb1/ | K319: https://old.reddit.com/r/cats/comments/1vf38ox/found_this_kitten_at_a_gas_station_and_trying_to/
... A650: r/OneOrangeBraincell | B650: t3_1ve5pof | C650: This is Cheddar. He is very polite | D650: t1_p1el4ss | E650: 0 | F650: misslavenderlemon | G650: 46237.32 | H650: 833 | I650: <image> | J650: https://old.reddit.com/r/OneOrangeBraincell/comments/1ve5pof/this_is_cheddar_he_is_very_polite/p1el4ss/ | K650: https://old.reddit.com/r/OneOrangeBraincell/comments/1ve5pof/this_is_cheddar_he_is_very_polite/
A651: r/OneOrangeBraincell | B651: t3_1ve5pof | C651: This is Cheddar. He is very polite | E651: 0 | G651: 46237.281 | H651: 753 | I651: [removed] | J651: https://old.reddit.com/r/OneOrangeBraincell/comments/1ve5pof/this_is_cheddar_he_is_very_polite/p1ei2ac/ | K651: https://old.reddit.com/r/OneOrangeBraincell/comments/1ve5pof/this_is_cheddar_he_is_very_polite/
A652: r/OneOrangeBraincell | B652: t3_1ve5pof | C652: This is Cheddar. He is very polite | D652: t1_p1ei2ac | E652: 0 | F652: Naktsvilks | G652: 46237.302 | H652: 753 | I652: I dunno about little, he's the largest cat we have, but handsome absolutely. And so pettable | J652: https://old.reddit.com/r/OneOrangeBraincell/comments/1ve5pof/this_is_cheddar_he_is_very_polite/p1ei2ac/ | K652: https://old.reddit.com/r/OneOrangeBraincell/comments/1ve5pof/this_is_cheddar_he_is_very_polite/
A653: r/OneOrangeBraincell | B653: t3_1ve5pof | C653: This is Cheddar. He is very polite | D653: t1_p1egvfz | E653: 0 | F653: Davorian | G653: 46237.295 | H653: 624 | I653: He looks very deferential. Many scritches wished. | J653: https://old.reddit.com/r/OneOrangeBraincell/comments/1ve5pof/this_is_cheddar_he_is_very_polite/p1egvfz/ | K653: https://old.reddit.com/r/OneOrangeBraincell/comments/1ve5pof/this_is_cheddar_he_is_very_polite/
A654: r/OneOrangeBraincell | B654: t3_1ve5pof | C654: This is Cheddar. He is very polite | D654: t1_p1elf2g | E654: 0 | F654: Elastichedgehog | G654: 46237.322 | H654: 470 | I654: He's just a baby | J654: https://old.reddit.com/r/OneOrangeBraincell/comments/1ve5pof/this_is_cheddar_he_is_very_polite/p1elf2g/ | K654: https://old.reddit.com/r/OneOrangeBraincell/comments/1ve5pof/this_is_cheddar_he_is_very_polite/
A655: r/OneOrangeBraincell | B655: t3_1ve5pof | C655: This is Cheddar. He is very polite | D655: t1_p1ej6vo | E655: 0 | F655: QuirkyDunmer | G655: 46237.309 | H655: 408 | I655: His wee turned out paws 😭🧡 | J655: https://old.reddit.com/r/OneOrangeBraincell/comments/1ve5pof/this_is_cheddar_he_is_very_polite/p1ej6vo/ | K655: https://old.reddit.com/r/OneOrangeBraincell/comments/1ve5pof/this_is_cheddar_he_is_very_polite/
A656: r/OneOrangeBraincell | B656: t3_1ve5pof | C656: This is Cheddar. He is very polite | D656: t1_p1ehyq0 | E656: 0 | F656: Naktsvilks | G656: 46237.302 | H656: 396 | I656: Many scritches delivered. He says "purr" | J656: https://old.reddit.com/r/OneOrangeBraincell/comments/1ve5pof/this_is_cheddar_he_is_very_polite/p1ehyq0/ | K656: https://old.reddit.com/r/OneOrangeBraincell/comments/1ve5pof/this_is_cheddar_he_is_very_polite/
A657: r/OneOrangeBraincell | B657: t3_1ve5pof | C657: This is Cheddar. He is very polite | D657: t1_p1ezr79 | E657: 0 | F657: Smooth_Flow5140 | G657: 46237.406 | H657: 299 | I657: <image> | J657: https://old.reddit.com/r/OneOrangeBraincell/comments/1ve5pof/this_is_cheddar_he_is_very_polite/p1ezr79/ | K657: https://old.reddit.com/r/OneOrangeBraincell/comments/1ve5pof/this_is_cheddar_he_is_very_polite/
A658: r/OneOrangeBraincell | B658: t3_1ve5pof | C658: This is Cheddar. He is very polite | D658: t1_p1eonlh | E658: 0 | F658: Naktsvilks | G658: 46237.341 | H658: 296 | I658: Older photo, as it is currently not petting-o-clock for him yet <image> | J658: https://old.reddit.com/r/OneOrangeBraincell/comments/1ve5pof/this_is_cheddar_he_is_very_polite/p1eonlh/ | K658: https://old.reddit.com/r/OneOrangeBraincell/comments/1ve5pof/this_is_cheddar_he_is_very_polite/
A659: r/OneOrangeBraincell | B659: t3_1ve5pof | C659: This is Cheddar. He is very polite | D659: t1_p1g7n5u | E659: 0 | F659: misslavenderlemon | G659: 46237.588 | H659: 226 | I659: <image> | J659: https://old.reddit.com/r/OneOrangeBraincell/comments/1ve5pof/this_is_cheddar_he_is_very_polite/p1g7n5u/ | K659: https://old.reddit.com/r/OneOrangeBraincell/comments/1ve5pof/this_is_cheddar_he_is_very_polite/
A660: r/OneOrangeBraincell | B660: t3_1ve5pof | C660: This is Cheddar. He is very polite | D660: t1_p1ejmlh | E660: 0 | F660: Naktsvilks | G660: 46237.311 | H660: 203 | I660: Ikr? He sits like this constantly! Little ballerina | J660: https://old.reddit.com/r/OneOrangeBraincell/comments/1ve5pof/this_is_cheddar_he_is_very_polite/p1ejmlh/ | K660: https://old.reddit.com/r/OneOrangeBraincell/comments/1ve5pof/this_is_cheddar_he_is_very_polite/
A661: r/OneOrangeBraincell | B661: t3_1ve5pof | C661: This is Cheddar. He is very polite | D661: t1_p1ejl3v | E661: 0 | F661: SQWRLLY1 | G661: 46237.311 | H661: 194 | I661: Please give Cheddar a boop from me. 🥰 | J661: https://old.reddit.com/r/OneOrangeBraincell/comments/1ve5pof/this_is_cheddar_he_is_very_polite/p1ejl3v/ | K661: https://old.reddit.com/r/OneOrangeBraincell/comments/1ve5pof/this_is_cheddar_he_is_very_polite/
A662: r/OneOrangeBraincell | B662: t3_1ve5pof | C662: This is Cheddar. He is very polite | D662: t1_p1ejoz2 | E662: 0 | F662: Naktsvilks | G662: 46237.312 | H662: 157 | I662: Delivered. He is confused | J662: https://old.reddit.com/r/OneOrangeBraincell/comments/1ve5pof/this_is_cheddar_he_is_very_polite/p1ejoz2/ | K662: https://old.reddit.com/r/OneOrangeBraincell/comments/1ve5pof/this_is_cheddar_he_is_very_polite/
A663: r/OneOrangeBraincell | B663: t3_1ve5pof | C663: This is Cheddar. He is very polite | D663: t1_p1eqbxx | E663: 0 | F663: eaglebtc | G663: 46237.351 | H663: 99 | I663: I'm sorry but he seems to have a case of /r/NoodleBones. | J663: https://old.reddit.com/r/OneOrangeBraincell/comments/1ve5pof/this_is_cheddar_he_is_very_polite/p1eqbxx/ | K663: https://old.reddit.com/r/OneOrangeBraincell/comments/1ve5pof/this_is_cheddar_he_is_very_polite/
... A680: r/OneOrangeBraincell | B680: t3_1ve5pof | C680: This is Cheddar. He is very polite | D680: t1_p1ej7o0 | E680: 0 | F680: arclightrg | G680: 46237.309 | H680: 29 | I680: Hello cheddar. Thou art a handsome orange. | J680: https://old.reddit.com/r/OneOrangeBraincell/comments/1ve5pof/this_is_cheddar_he_is_very_polite/p1ej7o0/ | K680: https://old.reddit.com/r/OneOrangeBraincell/comments/1ve5pof/this_is_cheddar_he_is_very_polite/
A681: r/OneOrangeBraincell | B681: t3_1ve5pof | C681: This is Cheddar. He is very polite | D681: t1_p1enfn6 | E681: 0 | F681: Valuable-Wait-4783 | G681: 46237.334 | H681: 27 | J681: https://old.reddit.com/r/OneOrangeBraincell/comments/1ve5pof/this_is_cheddar_he_is_very_polite/p1enfn6/ | K681: https://old.reddit.com/r/OneOrangeBraincell/comments/1ve5pof/this_is_cheddar_he_is_very_polite/
A682: r/OneOrangeBraincell | B682: t3_1ve5pof | C682: This is Cheddar. He is very polite | D682: t1_p1elqb7 | E682: 0 | F682: sundayfunday78 | G682: 46237.324 | H682: 24 | I682: He has an “I’m listening” vibe about him. Such a handsome boy. | J682: https://old.reddit.com/r/OneOrangeBraincell/comments/1ve5pof/this_is_cheddar_he_is_very_polite/p1elqb7/ | K682: https://old.reddit.com/r/OneOrangeBraincell/comments/1ve5pof/this_is_cheddar_he_is_very_polite/
...

Sheet 社区汇总
A1: 社区 | B1: 帖子行数 | C1: 有缩略图 | D1: 零评论帖 | E1: 分数隐藏/零 | F1: 评论覆盖帖 ID | G1: 抓取可见评论 | H1: 未展开占位
A2: r/Cats | B2: 300 | C2: 271 | D2: 32 | E2: 1 | F2: t3_1vf38ox | G2: 499 | H2: 73
A3: r/aww | B3: 300 | C3: 299 | D3: 40 | E3: 2 | F3: t3_1vejhaq | G3: 149 | H3: 0
A4: r/OneOrangeBraincell | B4: 300 | C4: 284 | D4: 40 | E4: 2 | F4: t3_1ve5pof | G4: 346 | H4: 0
A5: r/AnimalsBeingDerps | B5: 300 | C5: 296 | D5: 5 | E5: 1 | F5: t3_1uwss5p | G5: 259 | H5: 0
A6: r/blackcats | B6: 300 | C6: 288 | D6: 65 | E6: 1 | F6: t3_1vcqklb | G6: 271 | H6: 0
A7: r/CatDistributionSystem | B7: 300 | C7: 293 | D7: 0 | E7: 1 | F7: t3_1uqpi7u | G7: 482 | H7: 17
A8: r/TuxedoCats | B8: 300 | C8: 300 | D8: 40 | E8: 0 | F8: t3_1vcne63 | G8: 102 | H8: 0
A9: r/AnimalsBeingBros | B9: 300 | C9: 258 | D9: 2 | E9: 0 | F9: t3_1lvqybf | G9: 439 | H9: 67
A10: r/Catswithjobs | B10: 300 | C10: 298 | D10: 0 | E10: 0 | F10: t3_1v2we6u | G10: 252 | H10: 0
A11: r/WhatsWrongWithYourDog | B11: 300 | C11: 276 | D11: 11 | E11: 0 | F11: t3_1uv0ibg | G11: 476 | H11: 32
A12: r/rarepuppers | B12: 300 | C12: 300 | D12: 8 | E12: 1 | F12: t3_1vdxqqq | G12: 134 | H12: 0
